Workbook

Sheet Pricing Tool
A1: PULLEY — PRICING TOOL (VTIP)
A2: Customer Name : | B2: XYZ PVT LTD
A3: Final Destination: | F3: Payment Terms | G3: Ex Works Hyderabad | H3: Incoterms | I3: Ex Works Hyderabad | K3: Date: | L3: 46196 | M3: Date: | N3: Date: | O3: Date: | P3: Date: | Q3: Date: | R3: Date: | S3: Date:
A4: Techinical Data: | B4: Mr.Adam | F4: Delivery Time: | G4: 18 Weeks | H4: Version: | I4: Ver-1
A5: PARAMETER | B5: Unit | C5: MODEL 1 | D5: MODEL 2 | E5: MODEL 3 | F5: MODEL 4 | G5: MODEL 5 | H5: MODEL 6 | I5: MODEL 7 | J5: MODEL 8 | K5: MODEL 9 | L5: MODEL 10 | M5: MODEL 11 | N5: MODEL 12 | O5: MODEL 13 | P5: MODEL 14 | Q5: MODEL 15 | R5: MODEL 16 | S5: MODEL 17
A6: 1. PROJECT INFORMATION
A7: Project / Quote Reference | B7: — | C7: ='TECH DATA SHEET'!C7 -> P0108789-Pulleys for -01352532 | D7: ='TECH DATA SHEET'!D7 -> P0108789-Pulleys for -01352532 | E7: ='TECH DATA SHEET'!E7 -> P0108789-Pulleys for -01352532 | F7: ='TECH DATA SHEET'!F7 -> P0108789-Pulleys for -01352532 | G7: ='TECH DATA SHEET'!G7 -> P0108789-Pulleys for -01352532 | H7: ='TECH DATA SHEET'!H7 -> P0108789-Pulleys for -01352532 | I7: ='TECH DATA SHEET'!I7 -> P0108789-Pulleys for -01352532 | J7: ='TECH DATA SHEET'!J7 -> P0108789-Pulleys for -01352532 | ... S7: ='TECH DATA SHEET'!S7 -> P0108789-Pulleys for -01352532
A8: Pulley Tag / Name | B8: — | C8: ='TECH DATA SHEET'!C8 -> pulley_1 | D8: ='TECH DATA SHEET'!D8 -> pulley_2 | E8: ='TECH DATA SHEET'!E8 -> pulley_3 | F8: ='TECH DATA SHEET'!F8 -> pulley_4 | G8: ='TECH DATA SHEET'!G8 -> pulley_5 | H8: ='TECH DATA SHEET'!H8 -> pulley_6 | I8: ='TECH DATA SHEET'!I8 -> pulley_7 | J8: ='TECH DATA SHEET'!J8 -> pulley_8 | ... S8: ='TECH DATA SHEET'!S8 -> pulley_17
A9: Pulley Structure | B9: — | C9: ='TECH DATA SHEET'!C9 -> live shaft pulley | D9: ='TECH DATA SHEET'!D9 -> live shaft pulley | E9: ='TECH DATA SHEET'!E9 -> live shaft pulley | F9: ='TECH DATA SHEET'!F9 -> live shaft pulley | G9: ='TECH DATA SHEET'!G9 -> live shaft pulley | H9: ='TECH DATA SHEET'!H9 -> live shaft pulley | I9: ='TECH DATA SHEET'!I9 -> live shaft pulley | J9: ='TECH DATA SHEET'!J9 -> live shaft pulley | ... S9: ='TECH DATA SHEET'!S9 -> live shaft pulley
A10: Number of Pulleys (qty) | B10: nos | C10: 1 | D10: ='TECH DATA SHEET'!D10 -> 3 | E10: ='TECH DATA SHEET'!E10 -> 2 | F10: ='TECH DATA SHEET'!F10 -> 1 | G10: ='TECH DATA SHEET'!G10 -> 2 | H10: ='TECH DATA SHEET'!H10 -> 2 | I10: ='TECH DATA SHEET'!I10 -> 4 | J10: ='TECH DATA SHEET'!J10 -> 3 | K10: ='TECH DATA SHEET'!K10 -> 7 | ... S10: ='TECH DATA SHEET'!S10 -> 1
A12: 2. PULLEY BODY DIMENSIONS | V12: 15 | W12: Thinkness
A13: Shell Outer Diameter Dshell | B13: mm | C13: ='TECH DATA SHEET'!C13 -> 600 | D13: ='TECH DATA SHEET'!D13 -> 600 | E13: ='TECH DATA SHEET'!E13 -> 600 | F13: ='TECH DATA SHEET'!F13 -> 600 | G13: ='TECH DATA SHEET'!G13 -> 630 | H13: ='TECH DATA SHEET'!H13 -> 500 | I13: ='TECH DATA SHEET'!I13 -> 500 | J13: ='TECH DATA SHEET'!J13 -> 400 | ... S13: ='TECH DATA SHEET'!S13 -> 650 | V13: =457-20 -> 437 | W13: ID
A14: Shell Face Width Lface | B14: mm | C14: ='TECH DATA SHEET'!C14 -> 1300 | D14: ='TECH DATA SHEET'!D14 -> 1150 | E14: ='TECH DATA SHEET'!E14 -> 1150 | F14: ='TECH DATA SHEET'!F14 -> 1150 | G14: ='TECH DATA SHEET'!G14 -> 1400 | H14: ='TECH DATA SHEET'!H14 -> 1700 | I14: ='TECH DATA SHEET'!I14 -> 1400 | J14: ='TECH DATA SHEET'!J14 -> 1700 | ... S14: ='TECH DATA SHEET'!S14 -> 1200 | V14: =V13+15+15 -> 467 | W14: OD
A15: Shell Raw Thickness | B15: mm | C15: ='TECH DATA SHEET'!C15+5+3 -> 30 | D15: ='TECH DATA SHEET'!D15+5+3 -> 30 | E15: ='TECH DATA SHEET'!E15+5+3 -> 40 | F15: ='TECH DATA SHEET'!F15+5+3 -> 40 | G15: ='TECH DATA SHEET'!G15+5+3 -> 30 | H15: ='TECH DATA SHEET'!H15+5+3 -> 30 | I15: ='TECH DATA SHEET'!I15+5+3 -> 30 | J15: ='TECH DATA SHEET'!J15+5+3 -> 30 | ... S15: ='TECH DATA SHEET'!S15+5+3 -> 30 | V15: =(V14-V12)*3.141593+(120) -> 1540 | W15: Shell Legth Calc
A16: Sheet Width | B16: mm | C16: ='TECH DATA SHEET'!C16 -> 1300 | D16: ='TECH DATA SHEET'!D16 -> 1150 | E16: ='TECH DATA SHEET'!E16 -> 1150 | F16: ='TECH DATA SHEET'!F16 -> 1150 | G16: ='TECH DATA SHEET'!G16 -> 1400 | H16: ='TECH DATA SHEET'!H16 -> 1700 | I16: ='TECH DATA SHEET'!I16 -> 1400 | J16: ='TECH DATA SHEET'!J16 -> 1700 | ... S16: ='TECH DATA SHEET'!S16 -> 1200
A17: Sheet Length | B17: mm | C17: =(C13+10-C15)*3.141593+100 -> 1922.1239 | D17: =(D13-D15)*3.141593 -> 1790.708 | E17: =(E13-E15)*3.141593 -> 1759.2921 | F17: =(F13-F15)*3.141593 -> 1759.2921 | G17: =(G13-G15)*3.141593 -> 1884.9558 | H17: =(H13-H15)*3.141593 -> 1476.5487 | I17: =(I13-I15)*3.141593 -> 1476.5487 | J17: =(J13-J15)*3.141593 -> 1162.3894 | K17: =(K13+8-K15)*3.141593+100 -> 1287.5222 | L17: =(L13+8-L15)*3.141593+100 -> 1287.5222 | M17: =(M13+8-M15)*3.141593+100 -> 1601.6815 | N17: =(N13+8-N15)*3.141593+100 -> 2010.0885 | O17: =(O13+8-O15)*3.141593+100 -> 1287.5222 | P17: =(P13+8-P15)*3.141593+100 -> 1601.6815 | Q17: =(Q13+8-Q15)*3.141593+100 -> 2010.0885 | R17: =(R13+8-R15)*3.141593+100 -> 2544.1594 | S17: =(S13+8-S15)*3.141593+100 -> 2072.9204 | V17: Thik*width*lentght*Mat dencity
A18: Overall Pulley Diameter with Lagging | B18: mm | C18: ='TECH DATA SHEET'!C18 -> 624 | D18: ='TECH DATA SHEET'!D18 -> 624 | E18: ='TECH DATA SHEET'!E18 -> 624 | F18: ='TECH DATA SHEET'!F18 -> 624 | G18: ='TECH DATA SHEET'!G18 -> 654 | H18: ='TECH DATA SHEET'!H18 -> 524 | I18: ='TECH DATA SHEET'!I18 -> 524 | J18: ='TECH DATA SHEET'!J18 -> 424 | ... S18: ='TECH DATA SHEET'!S18 -> 674 | V18: =15*(711/1000)*(1540/1000)*7.85 -> 128.92918
A19: Bearing Housing Distance L1 | B19: mm | C19: ='TECH DATA SHEET'!C19 -> 1650 | D19: ='TECH DATA SHEET'!D19 -> 1525 | E19: ='TECH DATA SHEET'!E19 -> 1525 | F19: ='TECH DATA SHEET'!F19 -> 1525 | G19: ='TECH DATA SHEET'!G19 -> 1665 | H19: ='TECH DATA SHEET'!H19 -> 1955 | I19: ='TECH DATA SHEET'!I19 -> 1665 | J19: ='TECH DATA SHEET'!J19 -> 1955 | ... S19: ='TECH DATA SHEET'!S19 -> 1465
A20: Total Pulley Mass mtotal | B20: kg | C20: ='TECH DATA SHEET'!C20 -> 762.81795 | D20: ='TECH DATA SHEET'!D20 -> 708.48558 | E20: ='TECH DATA SHEET'!E20 -> 838.09164 | F20: ='TECH DATA SHEET'!F20 -> 832.02298 | G20: ='TECH DATA SHEET'!G20 -> 721.12586 | H20: ='TECH DATA SHEET'!H20 -> 607.87151 | I20: ='TECH DATA SHEET'!I20 -> 517.70289 | J20: ='TECH DATA SHEET'!J20 -> 449.43615 | ... S20: ='TECH DATA SHEET'!S20 -> 833.96638
A21: Sheel Plate Weight (Kg) | B21: kg | C21: =(C15*(C16/1000)*(C17/1000)*7.85) -> 588.45824 | D21: =(D15*(D16/1000)*(D17/1000)*7.85) -> 484.9685 | E21: =(E15*(E16/1000)*(E17/1000)*7.85) -> 635.28037 | F21: =(F15*(F16/1000)*(F17/1000)*7.85) -> 635.28037 | G21: =(G15*(G16/1000)*(G17/1000)*7.85) -> 621.46993 | H21: =(H15*(H16/1000)*(H17/1000)*7.85) -> 591.13628 | I21: =(I15*(I16/1000)*(I17/1000)*7.85) -> 486.81811 | J21: =(J15*(J16/1000)*(J17/1000)*7.85) -> 465.3626 | ... S21: =(S15*(S16/1000)*(S17/1000)*7.85) -> 585.80731
A22: Shell Rate Per Kg | B22: INR | C22: ='Raw Forging Prices'!$I$14 -> 110 | D22: ='Raw Forging Prices'!$I$14 -> 110 | E22: ='Raw Forging Prices'!$I$14 -> 110 | F22: ='Raw Forging Prices'!$I$14 -> 110 | G22: ='Raw Forging Prices'!$I$14 -> 110 | H22: ='Raw Forging Prices'!$I$14 -> 110 | I22: ='Raw Forging Prices'!$I$14 -> 110 | J22: ='Raw Forging Prices'!$I$14 -> 110 | ... S22: ='Raw Forging Prices'!$I$14 -> 110
A23: 3. HUB SPECIFICATIONS
A24: Hub Type | B24: — | C24: ='TECH DATA SHEET'!C24 -> Profiled T/C-hub | D24: ='TECH DATA SHEET'!D24 -> Profiled T/C-hub | E24: ='TECH DATA SHEET'!E24 -> Profiled T/C-hub | F24: ='TECH DATA SHEET'!F24 -> Profiled T/C-hub | G24: ='TECH DATA SHEET'!G24 -> welded in solid hub | H24: ='TECH DATA SHEET'!H24 -> welded in solid hub | I24: ='TECH DATA SHEET'!I24 -> welded in solid hub | J24: ='TECH DATA SHEET'!J24 -> welded in solid hub | ... S24: ='TECH DATA SHEET'!S24 -> Profiled T/C-hub
A25: Hub Width Whub | B25: mm | C25: ='TECH DATA SHEET'!C25+5 -> 129 | D25: ='TECH DATA SHEET'!D25 -> 124 | E25: ='TECH DATA SHEET'!E25 -> 124 | F25: ='TECH DATA SHEET'!F25 -> 124 | G25: ='TECH DATA SHEET'!G25 -> 90 | H25: ='TECH DATA SHEET'!H25 -> 90 | I25: ='TECH DATA SHEET'!I25 -> 90 | J25: ='TECH DATA SHEET'!J25 -> 90 | K25: ='TECH DATA SHEET'!K25 -> 90 | ... S25: ='TECH DATA SHEET'!S25 -> 124
A26: Min. Outer Diameter of Hub DN | B26: mm | C26: ='TECH DATA SHEET'!C26+10 -> 405 | D26: ='TECH DATA SHEET'!D26 -> 395 | E26: ='TECH DATA SHEET'!E26 -> 395 | F26: ='TECH DATA SHEET'!F26 -> 405 | G26: ='TECH DATA SHEET'!G26 -> 335 | H26: ='TECH DATA SHEET'!H26 -> 335 | I26: ='TECH DATA SHEET'!I26 -> 335 | J26: ='TECH DATA SHEET'!J26 -> 335 | K26: ='TECH DATA SHEET'!K26 -> 335 | ... S26: ='TECH DATA SHEET'!S26 -> 395
A27: Hub Inner Diameter d_LD (= LD bore) | B27: mm | C27: ='TECH DATA SHEET'!C27-15 -> 225 | D27: ='TECH DATA SHEET'!D27 -> 240 | E27: ='TECH DATA SHEET'!E27 -> 240 | F27: ='TECH DATA SHEET'!F27 -> 250 | G27: ='TECH DATA SHEET'!G27 -> 200 | H27: ='TECH DATA SHEET'!H27 -> 200 | I27: ='TECH DATA SHEET'!I27 -> 200 | J27: ='TECH DATA SHEET'!J27 -> 200 | K27: ='TECH DATA SHEET'!K27 -> 200 | ... S27: ='TECH DATA SHEET'!S27 -> 240
A28: Hub Mass (est., 2 hubs) [auto] | B28: kg | C28: =2*PI()/4*((C26/1000)^2-(C27/1000)^2)*(C25/1000)*7850 -> 180.38163 | D28: =2*PI()/4*((D26/1000)^2-(D27/1000)^2)*(D25/1000)*7850 -> 150.49312 | E28: =2*PI()/4*((E26/1000)^2-(E27/1000)^2)*(E25/1000)*7850 -> 150.49312 | F28: =2*PI()/4*((F26/1000)^2-(F27/1000)^2)*(F25/1000)*7850 -> 155.23306 | G28: =2*PI()/4*((G26/1000)^2-(G27/1000)^2)*(G25/1000)*7850 -> 80.152965 | H28: =2*PI()/4*((H26/1000)^2-(H27/1000)^2)*(H25/1000)*7850 -> 80.152965 | I28: =2*PI()/4*((I26/1000)^2-(I27/1000)^2)*(I25/1000)*7850 -> 80.152965 | J28: =2*PI()/4*((J26/1000)^2-(J27/1000)^2)*(J25/1000)*7850 -> 80.152965 | ... S28: =2*PI()/4*((S26/1000)^2-(S27/1000)^2)*(S25/1000)*7850 -> 150.49312
A29: End Disk Per Kg | B29: INR | C29: ='Raw Forging Prices'!$J$14 -> 210 | D29: ='Raw Forging Prices'!$J$14 -> 210 | E29: ='Raw Forging Prices'!$J$14 -> 210 | F29: ='Raw Forging Prices'!$J$14 -> 210 | G29: ='Raw Forging Prices'!$J$14 -> 210 | H29: ='Raw Forging Prices'!$J$14 -> 210 | I29: ='Raw Forging Prices'!$J$14 -> 210 | J29: ='Raw Forging Prices'!$J$14 -> 210 | ... S29: ='Raw Forging Prices'!$J$14 -> 210
A30: 4. SHAFT SPECIFICATIONS
A31: Shaft Total Length Lshaft | B31: mm | C31: ='TECH DATA SHEET'!C31 -> 1820 | D31: ='TECH DATA SHEET'!D31 -> 1699 | E31: ='TECH DATA SHEET'!E31 -> 1695 | F31: ='TECH DATA SHEET'!F31 -> 1713 | G31: ='TECH DATA SHEET'!G31 -> 1803 | H31: ='TECH DATA SHEET'!H31 -> 2093 | I31: ='TECH DATA SHEET'!I31 -> 1803 | J31: ='TECH DATA SHEET'!J31 -> 2093 | ... S31: ='TECH DATA SHEET'!S31 -> 1885
A32: Shaft Centre Diameter d4 | B32: mm | C32: ='TECH DATA SHEET'!C32 -> 178 | D32: ='TECH DATA SHEET'!D32 -> 178 | E32: ='TECH DATA SHEET'!E32 -> 178 | F32: ='TECH DATA SHEET'!F32 -> 188 | G32: ='TECH DATA SHEET'!G32 -> 148 | H32: ='TECH DATA SHEET'!H32 -> 158 | I32: ='TECH DATA SHEET'!I32 -> 148 | J32: ='TECH DATA SHEET'!J32 -> 158 | ... S32: ='TECH DATA SHEET'!S32 -> 178
A33: Shaft Material | B33: — | C33: ='TECH DATA SHEET'!C33 -> 42CrMo4+QT | D33: ='TECH DATA SHEET'!D33 -> 42CrMo4+QT | E33: ='TECH DATA SHEET'!E33 -> 42CrMo4+QT | F33: ='TECH DATA SHEET'!F33 -> 42CrMo4+QT | G33: ='TECH DATA SHEET'!G33 -> 42CrMo4+QT | H33: ='TECH DATA SHEET'!H33 -> 42CrMo4+QT | I33: ='TECH DATA SHEET'!I33 -> 42CrMo4+QT | J33: ='TECH DATA SHEET'!J33 -> 42CrMo4+QT | ... S33: ='TECH DATA SHEET'!S33 -> 42CrMo4+QT
A34: Shaft Mass [auto-calculated] | B34: kg | C34: =PI()/4*(C32/1000)^2*C31/1000*7850 -> 355.52564 | D34: =PI()/4*(D32/1000)^2*D31/1000*7850 -> 331.88905 | E34: =PI()/4*(E32/1000)^2*E31/1000*7850 -> 331.10767 | F34: =PI()/4*(F32/1000)^2*F31/1000*7850 -> 373.27818 | G34: =PI()/4*(G32/1000)^2*G31/1000*7850 -> 243.48864 | H34: =PI()/4*(H32/1000)^2*H31/1000*7850 -> 322.13873 | I34: =PI()/4*(I32/1000)^2*I31/1000*7850 -> 243.48864 | J34: =PI()/4*(J32/1000)^2*J31/1000*7850 -> 322.13873 | ... S34: =PI()/4*(S32/1000)^2*S31/1000*7850 -> 368.22299
A35: Shaft Per Kg | B35: kg | C35: =IF(C33='Raw Forging Prices'!$B$4,'Raw Forging Prices'!$F$4,'Raw Forging Prices'!$F$3) -> 330 | D35: =IF(D33='Raw Forging Prices'!$B$4,'Raw Forging Prices'!$F$4,'Raw Forging Prices'!$F$3) -> 330 | E35: =IF(E33='Raw Forging Prices'!$B$4,'Raw Forging Prices'!$F$4,'Raw Forging Prices'!$F$3) -> 330 | F35: =IF(F33='Raw Forging Prices'!$B$4,'Raw Forging Prices'!$F$4,'Raw Forging Prices'!$F$3) -> 330 | G35: =IF(G33='Raw Forging Prices'!$B$4,'Raw Forging Prices'!$F$4,'Raw Forging Prices'!$F$3) -> 330 | H35: =IF(H33='Raw Forging Prices'!$B$4,'Raw Forging Prices'!$F$4,'Raw Forging Prices'!$F$3) -> 330 | I35: =IF(I33='Raw Forging Prices'!$B$4,'Raw Forging Prices'!$F$4,'Raw Forging Prices'!$F$3) -> 330 | J35: =IF(J33='Raw Forging Prices'!$B$4,'Raw Forging Prices'!$F$4,'Raw Forging Prices'!$F$3) -> 330 | ... S35: =IF(S33='Raw Forging Prices'!$B$4,'Raw Forging Prices'!$F$4,'Raw Forging Prices'!$F$3) -> 330
A36: 5. BEARINGS, HOUSINGS & SLEEVES
A37: Bearing 1 Designation | B37: — | C37: ='TECH DATA SHEET'!C37 -> 22232 CCK/W33 | D37: ='TECH DATA SHEET'!D37 -> 22234 CCK/W33 | E37: ='TECH DATA SHEET'!E37 -> 22232 CCK/W33 | F37: ='TECH DATA SHEET'!F37 -> 22236 CCK/W33 | G37: ='TECH DATA SHEET'!G37 -> 22228 CCK/W33 | H37: ='TECH DATA SHEET'!H37 -> 22228 CCK/W33 | I37: ='TECH DATA SHEET'!I37 -> 22228 CCK/W33 | J37: ='TECH DATA SHEET'!J37 -> 22228 CCK/W33 | ... S37: ='TECH DATA SHEET'!S37 -> 22232 CCK/W33
A38: Bearing 1 Price (INR/ea) | B38: INR | C38: =IFERROR(VLOOKUP(C37,BRG_DATA!$A:$C,3,0),0) -> 30000 | D38: =IFERROR(VLOOKUP(D37,BRG_DATA!$A:$C,3,0),0) -> 34000 | E38: =IFERROR(VLOOKUP(E37,BRG_DATA!$A:$C,3,0),0) -> 30000 | F38: =IFERROR(VLOOKUP(F37,BRG_DATA!$A:$C,3,0),0) -> 50322 | G38: =IFERROR(VLOOKUP(G37,BRG_DATA!$A:$C,3,0),0) -> 23593 | H38: =IFERROR(VLOOKUP(H37,BRG_DATA!$A:$C,3,0),0) -> 23593 | I38: =IFERROR(VLOOKUP(I37,BRG_DATA!$A:$C,3,0),0) -> 23593 | J38: =IFERROR(VLOOKUP(J37,BRG_DATA!$A:$C,3,0),0) -> 23593 | ... S38: =IFERROR(VLOOKUP(S37,BRG_DATA!$A:$C,3,0),0) -> 30000
A39: Bearing 2 Designation | B39: — | C39: ='TECH DATA SHEET'!C39 -> 22232 CCK/W33 | D39: ='TECH DATA SHEET'!D39 -> 22234 CCK/W33 | E39: ='TECH DATA SHEET'!E39 -> 22232 CCK/W33 | F39: ='TECH DATA SHEET'!F39 -> 22236 CCK/W33 | G39: ='TECH DATA SHEET'!G39 -> 22228 CCK/W33 | H39: ='TECH DATA SHEET'!H39 -> 22228 CCK/W33 | I39: ='TECH DATA SHEET'!I39 -> 22228 CCK/W33 | J39: ='TECH DATA SHEET'!J39 -> 22228 CCK/W33 | ... S39: ='TECH DATA SHEET'!S39 -> 22232 CCK/W33
A40: Bearing 2 Price (INR/ea) | B40: INR | C40: =IFERROR(VLOOKUP(C39,BRG_DATA!$A:$C,3,0),0) -> 30000 | D40: =IFERROR(VLOOKUP(D39,BRG_DATA!$A:$C,3,0),0) -> 34000 | E40: =IFERROR(VLOOKUP(E39,BRG_DATA!$A:$C,3,0),0) -> 30000 | F40: =IFERROR(VLOOKUP(F39,BRG_DATA!$A:$C,3,0),0) -> 50322 | G40: =IFERROR(VLOOKUP(G39,BRG_DATA!$A:$C,3,0),0) -> 23593 | H40: =IFERROR(VLOOKUP(H39,BRG_DATA!$A:$C,3,0),0) -> 23593 | I40: =IFERROR(VLOOKUP(I39,BRG_DATA!$A:$C,3,0),0) -> 23593 | J40: =IFERROR(VLOOKUP(J39,BRG_DATA!$A:$C,3,0),0) -> 23593 | ... S40: =IFERROR(VLOOKUP(S39,BRG_DATA!$A:$C,3,0),0) -> 30000
A41: Adapter Sleeve Code | B41: — | C41: ='TECH DATA SHEET'!C41 -> H 3132 | D41: ='TECH DATA SHEET'!D41 -> H 3134 | E41: ='TECH DATA SHEET'!E41 -> H 3132 | F41: ='TECH DATA SHEET'!F41 -> H 3136 | G41: ='TECH DATA SHEET'!G41 -> H 3128 | H41: ='TECH DATA SHEET'!H41 -> H 3128 | I41: ='TECH DATA SHEET'!I41 -> H 3128 | J41: ='TECH DATA SHEET'!J41 -> H 3128 | ... S41: ='TECH DATA SHEET'!S41 -> H 3132
A42: Sleeve Price (INR/ea) | B42: INR | C42: =IFERROR(VLOOKUP(C37,SL_DATA!$A:$D,4,0),0) -> 5000 | D42: =IFERROR(VLOOKUP(D37,SL_DATA!$A:$D,4,0),0) -> 5000 | E42: =IFERROR(VLOOKUP(E37,SL_DATA!$A:$D,4,0),0) -> 5000 | F42: =IFERROR(VLOOKUP(F37,SL_DATA!$A:$D,4,0),0) -> 13814 | G42: =IFERROR(VLOOKUP(G37,SL_DATA!$A:$D,4,0),0) -> 5816 | H42: =IFERROR(VLOOKUP(H37,SL_DATA!$A:$D,4,0),0) -> 5816 | I42: =IFERROR(VLOOKUP(I37,SL_DATA!$A:$D,4,0),0) -> 5816 | J42: =IFERROR(VLOOKUP(J37,SL_DATA!$A:$D,4,0),0) -> 5816 | ... S42: =IFERROR(VLOOKUP(S37,SL_DATA!$A:$D,4,0),0) -> 5000
A43: Housing Designation | B43: — | C43: ='TECH DATA SHEET'!C43 -> SNL 532 | D43: ='TECH DATA SHEET'!D43 -> SNL 3234 | E43: ='TECH DATA SHEET'!E43 -> SNL 532 | F43: ='TECH DATA SHEET'!F43 -> SNL 3138 | G43: ='TECH DATA SHEET'!G43 -> SNL 528 | H43: ='TECH DATA SHEET'!H43 -> SNL 528 | I43: ='TECH DATA SHEET'!I43 -> SNL 528 | J43: ='TECH DATA SHEET'!J43 -> SNL 528 | ... S43: ='TECH DATA SHEET'!S43 -> SNL532
A44: Housing Price (INR/ea) | B44: INR | C44: =IFERROR(VLOOKUP(C43,HSG_DATA!$B:$C,2,0),0) -> 39672 | D44: =IFERROR(VLOOKUP(D43,HSG_DATA!$B:$C,2,0),0) -> 0 | E44: =IFERROR(VLOOKUP(E43,HSG_DATA!$B:$C,2,0),0) -> 39672 | F44: =IFERROR(VLOOKUP(F43,HSG_DATA!$B:$C,2,0),0) -> 48472 | G44: =IFERROR(VLOOKUP(G43,HSG_DATA!$B:$C,2,0),0) -> 25766 | H44: =IFERROR(VLOOKUP(H43,HSG_DATA!$B:$C,2,0),0) -> 25766 | I44: =IFERROR(VLOOKUP(I43,HSG_DATA!$B:$C,2,0),0) -> 25766 | J44: =IFERROR(VLOOKUP(J43,HSG_DATA!$B:$C,2,0),0) -> 25766 | ... S44: =IFERROR(VLOOKUP(S43,HSG_DATA!$B:$C,2,0),0) -> 0
A45: Total Bearings + Sleeves + Housings (2× each) | B45: INR | C45: =2*(C38+C40+C42+C44) -> 209344 | D45: =2*(D38+D40+D42+D44) -> 146000 | E45: =2*(E38+E40+E42+E44) -> 209344 | F45: =2*(F38+F40+F42+F44) -> 325860 | G45: =2*(G38+G40+G42+G44) -> 157536 | H45: =2*(H38+H40+H42+H44) -> 157536 | I45: =2*(I38+I40+I42+I44) -> 157536 | J45: =2*(J38+J40+J42+J44) -> 157536 | ... S45: =2*(S38+S40+S42+S44) -> 130000
A47: 6. LAGGING
A48: Lagging Type | B48: — | C48: ='TECH DATA SHEET'!C48 -> Rubber vulc. 12mm | D48: ='TECH DATA SHEET'!D48 -> Rubber vulc. 12mm | E48: ='TECH DATA SHEET'!E48 -> Rubber vulc. 12mm | F48: ='TECH DATA SHEET'!F48 -> Rubber vulc. 12mm | G48: ='TECH DATA SHEET'!G48 -> Rubber vulc. 12mm | H48: ='TECH DATA SHEET'!H48 -> Rubber vulc. 12mm | I48: ='TECH DATA SHEET'!I48 -> Rubber vulc. 12mm | J48: ='TECH DATA SHEET'!J48 -> Rubber vulc. 12mm | ... S48: ='TECH DATA SHEET'!S48 -> Rubber vulc. 12mm
A49: Lagging Thickness | B49: mm | C49: ='TECH DATA SHEET'!C49 -> 12 | D49: ='TECH DATA SHEET'!D49 -> 12 | E49: ='TECH DATA SHEET'!E49 -> 12 | F49: ='TECH DATA SHEET'!F49 -> 12 | G49: ='TECH DATA SHEET'!G49 -> 12 | H49: ='TECH DATA SHEET'!H49 -> 12 | I49: ='TECH DATA SHEET'!I49 -> 12 | J49: ='TECH DATA SHEET'!J49 -> 12 | ... S49: ='TECH DATA SHEET'!S49 -> 12
A50: Lagging Area [auto: π × Dshell × Lface] | B50: m² | C50: =PI()*C13/1000*C14/1000 -> 2.4504423 | D50: =PI()*D13/1000*D14/1000 -> 2.1676989 | E50: =PI()*E13/1000*E14/1000 -> 2.1676989 | F50: =PI()*F13/1000*F14/1000 -> 2.1676989 | G50: =PI()*G13/1000*G14/1000 -> 2.7708847 | H50: =PI()*H13/1000*H14/1000 -> 2.6703538 | I50: =PI()*I13/1000*I14/1000 -> 2.1991149 | J50: =PI()*J13/1000*J14/1000 -> 2.136283 | ... S50: =PI()*S13/1000*S14/1000 -> 2.4504423
A51: Lagging Rate | B51: INR/m² | C51: =IFERROR(VLOOKUP(C48,LAG_DATA!$A:$C,3,0),0) -> 19387 | D51: =IFERROR(VLOOKUP(D48,LAG_DATA!$A:$C,3,0),0) -> 19387 | E51: =IFERROR(VLOOKUP(E48,LAG_DATA!$A:$C,3,0),0) -> 19387 | F51: =IFERROR(VLOOKUP(F48,LAG_DATA!$A:$C,3,0),0) -> 19387 | G51: =IFERROR(VLOOKUP(G48,LAG_DATA!$A:$C,3,0),0) -> 19387 | H51: =IFERROR(VLOOKUP(H48,LAG_DATA!$A:$C,3,0),0) -> 19387 | I51: =IFERROR(VLOOKUP(I48,LAG_DATA!$A:$C,3,0),0) -> 19387 | J51: =IFERROR(VLOOKUP(J48,LAG_DATA!$A:$C,3,0),0) -> 19387 | ... S51: =IFERROR(VLOOKUP(S48,LAG_DATA!$A:$C,3,0),0) -> 19387
A52: Lagging Cost [auto] | B52: INR | C52: =C50*C51 -> 47506.724 | D52: =D50*D51 -> 42025.179 | E52: =E50*E51 -> 42025.179 | F52: =F50*F51 -> 42025.179 | G52: =G50*G51 -> 53719.142 | H52: =H50*H51 -> 51770.148 | I52: =I50*I51 -> 42634.24 | J52: =J50*J51 -> 41416.119 | ... S52: =S50*S51 -> 47506.724
A54: 7. LOCKING DEVICE & DEAD SHAFT PARTS
A55: Locking Device Type | B55: — | C55: ='TECH DATA SHEET'!C55 -> NMTG N7036-170 × 240 | D55: ='TECH DATA SHEET'!D55 -> NMTG N7036-170 × 240 | E55: ='TECH DATA SHEET'!E55 -> NMTG N7036-170 × 240 | F55: ='TECH DATA SHEET'!F55 -> NMTG N7036-180 × 250 | G55: ='TECH DATA SHEET'!G55 -> NMTG N7036-140 × 200 | H55: ='TECH DATA SHEET'!H55 -> NMTG N7036-140 × 200 | I55: ='TECH DATA SHEET'!I55 -> NMTG N7036-140 × 200 | J55: ='TECH DATA SHEET'!J55 -> NMTG N7036-140 × 200 | ... S55: ='TECH DATA SHEET'!S55 -> NMTG N7036-170 × 240
A56: Locking Device INR Price | B56: INR | C56: =IFERROR(VLOOKUP(C55,LCD_DATA!$A$3:$C$7,3,0),0) -> 70000 | D56: =IFERROR(VLOOKUP(D55,LCD_DATA!$A$3:$C$7,3,0),0) -> 70000 | E56: =IFERROR(VLOOKUP(E55,LCD_DATA!$A$3:$C$7,3,0),0) -> 70000 | F56: =IFERROR(VLOOKUP(F55,LCD_DATA!$A$3:$C$7,3,0),0) -> 80000 | G56: =IFERROR(VLOOKUP(G55,LCD_DATA!$A$3:$C$7,3,0),0) -> 50000 | H56: =IFERROR(VLOOKUP(H55,LCD_DATA!$A$3:$C$7,3,0),0) -> 50000 | I56: =IFERROR(VLOOKUP(I55,LCD_DATA!$A$3:$C$7,3,0),0) -> 50000 | J56: =IFERROR(VLOOKUP(J55,LCD_DATA!$A$3:$C$7,3,0),0) -> 50000 | ... S56: =IFERROR(VLOOKUP(S55,LCD_DATA!$A$3:$C$7,3,0),0) -> 70000
A57: Dead Shaft Parts (inner tube, supports, seals) | B57: INR
A59: 8. SOURCING SELECTION — In-house or Outsource per Process
A60: Rolling / Bending Shell | B60: — | C60: In-house | D60: In-house | E60: In-house | F60: In-house | G60: In-house | H60: In-house | I60: In-house | J60: In-house | K60: In-house | L60: In-house | M60: In-house | N60: In-house | O60: In-house | P60: In-house | Q60: In-house | R60: In-house | S60: In-house
A61: Welding (Shell + Hub) | B61: — | C61: In-house | D61: In-house | E61: In-house | F61: In-house | G61: In-house | H61: In-house | I61: In-house | J61: In-house | K61: In-house | L61: In-house | M61: In-house | N61: In-house | O61: In-house | P61: In-house | Q61: In-house | R61: In-house | S61: In-house
A62: Stress Relief Annealing | B62: — | C62: Outsource | D62: Outsource | E62: Outsource | F62: Outsource | G62: Outsource | H62: Outsource | I62: Outsource | J62: Outsource | K62: Outsource | L62: Outsource | M62: Outsource | N62: Outsource | O62: Outsource | P62: Outsource | Q62: Outsource | R62: Outsource | S62: Outsource
A63: Turning / Machining (Body) | B63: — | C63: In-house | D63: In-house | E63: In-house | F63: In-house | G63: In-house | H63: In-house | I63: In-house | J63: In-house | K63: In-house | L63: In-house | M63: In-house | N63: In-house | O63: In-house | P63: In-house | Q63: In-house | R63: In-house | S63: In-house
A64: Lagging Application | B64: — | C64: Outsource | D64: Outsource | E64: Outsource | F64: Outsource | G64: Outsource | H64: Outsource | I64: Outsource | J64: Outsource | K64: Outsource | L64: Outsource | M64: Outsource | N64: Outsource | O64: Outsource | P64: Outsource | Q64: Outsource | R64: Outsource | S64: Outsource
A65: Static Balancing | B65: — | C65: In-house | D65: In-house | E65: In-house | F65: In-house | G65: In-house | H65: In-house | I65: In-house | J65: In-house | K65: In-house | L65: In-house | M65: In-house | N65: In-house | O65: In-house | P65: In-house | Q65: In-house | R65: In-house | S65: In-house
A66: Painting / Blasting | B66: — | C66: In-house | D66: In-house | E66: In-house | F66: In-house | G66: In-house | H66: In-house | I66: In-house | J66: In-house | K66: In-house | L66: In-house | M66: In-house | N66: In-house | O66: In-house | P66: In-house | Q66: In-house | R66: In-house | S66: In-house
A68: SECTION A — RAW MATERIALS COST
A69: A1. Shell / Body Material (IS 2062 E350) | B69: INR | C69: =C22*C21 -> 64730.407 | D69: =D22*D21 -> 53346.535 | E69: =E22*E21 -> 69880.841 | F69: =F22*F21 -> 69880.841 | G69: =G22*G21 -> 68361.692 | H69: =H22*H21 -> 65024.99 | I69: =I22*I21 -> 53549.992 | J69: =J22*J21 -> 51189.886 | ... S69: =S22*S21 -> 64438.804
A70: A2. End Disc / End Plate Material (IS 2062) | B70: INR | C70: ='Cost Rate Tables'!$C$13*C28 -> 24215.57 | D70: ='Cost Rate Tables'!$C$13*D28 -> 20203.148 | E70: =E29*E28 -> 31603.555 | F70: =F29*F28 -> 32598.942 | G70: =G29*G28 -> 16832.123 | H70: =H29*H28 -> 16832.123 | I70: =I29*I28 -> 16832.123 | J70: =J29*J28 -> 16832.123 | K70: =K29*K28 -> 16832.123 | L70: =L29*L28 -> 8079.1082 | ... S70: =S29*S28 -> 31603.555
A71: A3. Hub Material (Cast Steel GS-52) | B71: INR
A72: A4. Shaft Material (C45 / 42CrMo4+QT) | B72: INR | C72: =IF(C33="C45",'Cost Rate Tables'!C15,IF(C33="42CrMo4+QT",'Cost Rate Tables'!C16,'Cost Rate Tables'!C15))*C34 -> 83179.584 | D72: =IF(D33="C45",'Cost Rate Tables'!C15,IF(D33="42CrMo4+QT",'Cost Rate Tables'!C16,'Cost Rate Tables'!C15))*D34 -> 77649.513 | E72: =E35*E34 -> 109265.53 | F72: =F35*F34 -> 123181.8 | G72: =G35*G34 -> 80351.25 | H72: =H35*H34 -> 106305.78 | I72: =I35*I34 -> 80351.25 | J72: =J35*J34 -> 106305.78 | K72: =K35*K34 -> 80351.25 | L72: =L35*L34 -> 48443.287 | ... S72: =S35*S34 -> 121513.59
A73: A5. Weld Consumables (per kg pulley) | B73: INR | C73: =C21*'Cost Rate Tables'!$C$17 -> 3530.7495 | D73: =D21*'Cost Rate Tables'!$C$17 -> 2909.811 | E73: =E21*'Cost Rate Tables'!$C$17 -> 3811.6822 | F73: =F21*'Cost Rate Tables'!$C$17 -> 3811.6822 | G73: =G21*'Cost Rate Tables'!$C$17 -> 3728.8196 | H73: =H21*'Cost Rate Tables'!$C$17 -> 3546.8177 | I73: =I21*'Cost Rate Tables'!$C$17 -> 2920.9087 | J73: =J21*'Cost Rate Tables'!$C$17 -> 2792.1756 | ... S73: =S21*'Cost Rate Tables'!$C$17 -> 3514.8438
A74: A6. Greese (per kg pulley) | B74: INR | C74: =C28*'Cost Rate Tables'!$C$18 -> 3246.8693 | D74: =D28*'Cost Rate Tables'!$C$18 -> 2708.8761 | E74: =E28*'Cost Rate Tables'!$C$18 -> 2708.8761 | F74: =F28*'Cost Rate Tables'!$C$18 -> 2794.1951 | G74: =G28*'Cost Rate Tables'!$C$18 -> 1442.7534 | H74: =H28*'Cost Rate Tables'!$C$18 -> 1442.7534 | I74: =I28*'Cost Rate Tables'!$C$18 -> 1442.7534 | J74: =J28*'Cost Rate Tables'!$C$18 -> 1442.7534 | ... S74: =S28*'Cost Rate Tables'!$C$18 -> 2708.8761
A75: TOTAL RAW MATERIALS COST (A) | C75: =SUM(C69:C74) -> 178903.18 | D75: =SUM(D69:D74) -> 156817.88 | E75: =SUM(E69:E74) -> 217270.49 | F75: =SUM(F69:F74) -> 232267.46 | G75: =SUM(G69:G74) -> 170716.64 | H75: =SUM(H69:H74) -> 193152.46 | I75: =SUM(I69:I74) -> 155097.03 | J75: =SUM(J69:J74) -> 178562.72 | ... S75: =SUM(S69:S74) -> 223779.66
A77: SECTION B — ANCILLARY PARTS (Bearings, Sleeves, Housings, Locking Device, Lagging)
A78: B1. Bearings (2× Drive + 2× Non-Drive) | B78: INR | C78: =(C38+C40) -> 60000 | D78: =(D38+D40) -> 68000 | E78: =(E38+E40) -> 60000 | F78: =(F38+F40) -> 100644 | G78: =(G38+G40) -> 47186 | H78: =(H38+H40) -> 47186 | I78: =(I38+I40) -> 47186 | J78: =(J38+J40) -> 47186 | ... S78: =(S38+S40) -> 60000
A79: B2. Adapter Sleeves (2×) | B79: INR | C79: =2*C42 -> 10000 | D79: =2*D42 -> 10000 | E79: =2*E42 -> 10000 | F79: =2*F42 -> 27628 | G79: =2*G42 -> 11632 | H79: =2*H42 -> 11632 | I79: =2*I42 -> 11632 | J79: =2*J42 -> 11632 | ... S79: =2*S42 -> 10000
A80: B3. Bearing Housings (2×) | B80: INR | C80: =2*C44 -> 79344 | D80: =2*D44 -> 0 | E80: =2*E44 -> 79344 | F80: =2*F44 -> 96944 | G80: =2*G44 -> 51532 | H80: =2*H44 -> 51532 | I80: =2*I44 -> 51532 | J80: =2*J44 -> 51532 | ... S80: =2*S44 -> 0
A81: B4. Locking Device | B81: INR | C81: =C56*2 -> 140000 | D81: =D56*2 -> 140000 | E81: =E56*2 -> 140000 | F81: =F56*2 -> 160000 | G81: =G56*2 -> 100000 | H81: =H56*2 -> 100000 | I81: =I56*2 -> 100000 | J81: =J56*2 -> 100000 | ... S81: =S56*2 -> 140000
A82: B5. Lagging (supply & material only) | B82: INR
A83: B6. Dead Shaft Parts (inner tube, supports, seals) | B83: INR
A84: TOTAL ANCILLARY PARTS COST (B) | C84: =SUM(C78:C83) -> 289344 | D84: =SUM(D78:D83) -> 218000 | E84: =SUM(E78:E83) -> 289344 | F84: =SUM(F78:F83) -> 385216 | G84: =SUM(G78:G83) -> 210350 | H84: =SUM(H78:H83) -> 210350 | I84: =SUM(I78:I83) -> 210350 | J84: =SUM(J78:J83) -> 210350 | ... S84: =SUM(S78:S83) -> 210000
A86: SECTION C — IN-HOUSE PROCESSING COST (linked to 'In-House Hours' sheet totals)
A87: C1. Rolling / Bending Shell | B87: INR | C87: =_xlfn.IFNA(VLOOKUP($A87,'In-House Hours'!$D$5:$BU$10,6+(COLUMN(A87)-1)*4,FALSE),0) -> 42666.162 | D87: =_xlfn.IFNA(VLOOKUP($A87,'In-House Hours'!$D$5:$BU$10,6+(COLUMN(B87)-1)*4,FALSE),0) -> 42666.162 | E87: =_xlfn.IFNA(VLOOKUP($A87,'In-House Hours'!$D$5:$BU$10,6+(COLUMN(C87)-1)*4,FALSE),0) -> 42666.162 | F87: =_xlfn.IFNA(VLOOKUP($A87,'In-House Hours'!$D$5:$BU$10,6+(COLUMN(D87)-1)*4,FALSE),0) -> 42666.162 | G87: =_xlfn.IFNA(VLOOKUP($A87,'In-House Hours'!$D$5:$BU$10,6+(COLUMN(E87)-1)*4,FALSE),0) -> 42666.162 | H87: =_xlfn.IFNA(VLOOKUP($A87,'In-House Hours'!$D$5:$BU$10,6+(COLUMN(F87)-1)*4,FALSE),0) -> 42666.162 | I87: =_xlfn.IFNA(VLOOKUP($A87,'In-House Hours'!$D$5:$BU$10,6+(COLUMN(G87)-1)*4,FALSE),0) -> 42666.162 | J87: =_xlfn.IFNA(VLOOKUP($A87,'In-House Hours'!$D$5:$BU$10,6+(COLUMN(H87)-1)*4,FALSE),0) -> 42666.162 | ... S87: =_xlfn.IFNA(VLOOKUP($A87,'In-House Hours'!$D$5:$BU$10,6+(COLUMN(Q87)-1)*4,FALSE),0) -> 42666.162
A88: C2. Welding – Shell & Hub | B88: INR | C88: =_xlfn.IFNA(VLOOKUP($A88,'In-House Hours'!$D$5:$BU$10,6+(COLUMN(A88)-1)*4,FALSE),0) -> 101513.9 | D88: =_xlfn.IFNA(VLOOKUP($A88,'In-House Hours'!$D$5:$BU$10,6+(COLUMN(B88)-1)*4,FALSE),0) -> 101513.9 | E88: =_xlfn.IFNA(VLOOKUP($A88,'In-House Hours'!$D$5:$BU$10,6+(COLUMN(C88)-1)*4,FALSE),0) -> 101513.9 | F88: =_xlfn.IFNA(VLOOKUP($A88,'In-House Hours'!$D$5:$BU$10,6+(COLUMN(D88)-1)*4,FALSE),0) -> 71844.381 | G88: =_xlfn.IFNA(VLOOKUP($A88,'In-House Hours'!$D$5:$BU$10,6+(COLUMN(E88)-1)*4,FALSE),0) -> 101513.9 | H88: =_xlfn.IFNA(VLOOKUP($A88,'In-House Hours'!$D$5:$BU$10,6+(COLUMN(F88)-1)*4,FALSE),0) -> 101513.9 | I88: =_xlfn.IFNA(VLOOKUP($A88,'In-House Hours'!$D$5:$BU$10,6+(COLUMN(G88)-1)*4,FALSE),0) -> 101513.9 | J88: =_xlfn.IFNA(VLOOKUP($A88,'In-House Hours'!$D$5:$BU$10,6+(COLUMN(H88)-1)*4,FALSE),0) -> 101513.9 | ... S88: =_xlfn.IFNA(VLOOKUP($A88,'In-House Hours'!$D$5:$BU$10,6+(COLUMN(Q88)-1)*4,FALSE),0) -> 101513.9
A89: C3. Machining / Turning Body | B89: INR | C89: =_xlfn.IFNA(VLOOKUP($A89,'In-House Hours'!$D$5:$BU$10,6+(COLUMN(A89)-1)*4,FALSE),0) -> 43753.948 | D89: =_xlfn.IFNA(VLOOKUP($A89,'In-House Hours'!$D$5:$BU$10,6+(COLUMN(B89)-1)*4,FALSE),0) -> 43753.948 | E89: =_xlfn.IFNA(VLOOKUP($A89,'In-House Hours'!$D$5:$BU$10,6+(COLUMN(C89)-1)*4,FALSE),0) -> 43753.948 | F89: =_xlfn.IFNA(VLOOKUP($A89,'In-House Hours'!$D$5:$BU$10,6+(COLUMN(D89)-1)*4,FALSE),0) -> 43753.948 | G89: =_xlfn.IFNA(VLOOKUP($A89,'In-House Hours'!$D$5:$BU$10,6+(COLUMN(E89)-1)*4,FALSE),0) -> 43753.948 | H89: =_xlfn.IFNA(VLOOKUP($A89,'In-House Hours'!$D$5:$BU$10,6+(COLUMN(F89)-1)*4,FALSE),0) -> 43753.948 | I89: =_xlfn.IFNA(VLOOKUP($A89,'In-House Hours'!$D$5:$BU$10,6+(COLUMN(G89)-1)*4,FALSE),0) -> 43753.948 | J89: =_xlfn.IFNA(VLOOKUP($A89,'In-House Hours'!$D$5:$BU$10,6+(COLUMN(H89)-1)*4,FALSE),0) -> 43753.948 | ... S89: =_xlfn.IFNA(VLOOKUP($A89,'In-House Hours'!$D$5:$BU$10,6+(COLUMN(Q89)-1)*4,FALSE),0) -> 43753.948
A90: C4. Assembly + Engineering | B90: INR | C90: =_xlfn.IFNA(VLOOKUP($A90,'In-House Hours'!$D$5:$BU$10,6+(COLUMN(A90)-1)*4,FALSE),0) -> 31172.386 | D90: =_xlfn.IFNA(VLOOKUP($A90,'In-House Hours'!$D$5:$BU$10,6+(COLUMN(B90)-1)*4,FALSE),0) -> 31172.386 | E90: =_xlfn.IFNA(VLOOKUP($A90,'In-House Hours'!$D$5:$BU$10,6+(COLUMN(C90)-1)*4,FALSE),0) -> 31172.386 | F90: =_xlfn.IFNA(VLOOKUP($A90,'In-House Hours'!$D$5:$BU$10,6+(COLUMN(D90)-1)*4,FALSE),0) -> 31172.386 | G90: =_xlfn.IFNA(VLOOKUP($A90,'In-House Hours'!$D$5:$BU$10,6+(COLUMN(E90)-1)*4,FALSE),0) -> 31172.386 | H90: =_xlfn.IFNA(VLOOKUP($A90,'In-House Hours'!$D$5:$BU$10,6+(COLUMN(F90)-1)*4,FALSE),0) -> 31172.386 | I90: =_xlfn.IFNA(VLOOKUP($A90,'In-House Hours'!$D$5:$BU$10,6+(COLUMN(G90)-1)*4,FALSE),0) -> 31172.386 | J90: =_xlfn.IFNA(VLOOKUP($A90,'In-House Hours'!$D$5:$BU$10,6+(COLUMN(H90)-1)*4,FALSE),0) -> 31172.386 | ... S90: =_xlfn.IFNA(VLOOKUP($A90,'In-House Hours'!$D$5:$BU$10,6+(COLUMN(Q90)-1)*4,FALSE),0) -> 31172.386
A91: C5. Testing / Inspection / QC | B91: INR | C91: =_xlfn.IFNA(VLOOKUP($A91,'In-House Hours'!$D$5:$BU$10,6+(COLUMN(A91)-1)*4,FALSE),0) -> 19826.84 | D91: =_xlfn.IFNA(VLOOKUP($A91,'In-House Hours'!$D$5:$BU$10,6+(COLUMN(B91)-1)*4,FALSE),0) -> 19826.84 | E91: =_xlfn.IFNA(VLOOKUP($A91,'In-House Hours'!$D$5:$BU$10,6+(COLUMN(C91)-1)*4,FALSE),0) -> 19826.84 | F91: =_xlfn.IFNA(VLOOKUP($A91,'In-House Hours'!$D$5:$BU$10,6+(COLUMN(D91)-1)*4,FALSE),0) -> 19826.84 | G91: =_xlfn.IFNA(VLOOKUP($A91,'In-House Hours'!$D$5:$BU$10,6+(COLUMN(E91)-1)*4,FALSE),0) -> 19826.84 | H91: =_xlfn.IFNA(VLOOKUP($A91,'In-House Hours'!$D$5:$BU$10,6+(COLUMN(F91)-1)*4,FALSE),0) -> 19826.84 | I91: =_xlfn.IFNA(VLOOKUP($A91,'In-House Hours'!$D$5:$BU$10,6+(COLUMN(G91)-1)*4,FALSE),0) -> 19826.84 | J91: =_xlfn.IFNA(VLOOKUP($A91,'In-House Hours'!$D$5:$BU$10,6+(COLUMN(H91)-1)*4,FALSE),0) -> 19826.84 | ... S91: =_xlfn.IFNA(VLOOKUP($A91,'In-House Hours'!$D$5:$BU$10,6+(COLUMN(Q91)-1)*4,FALSE),0) -> 19826.84
A92: C6. Painting & Surface Prep | B92: INR | C92: =_xlfn.IFNA(VLOOKUP($A92,'In-House Hours'!$D$5:$BU$10,6+(COLUMN(A92)-1)*4,FALSE),0) -> 0 | D92: =_xlfn.IFNA(VLOOKUP($A92,'In-House Hours'!$D$5:$BU$10,6+(COLUMN(B92)-1)*4,FALSE),0) -> 0 | E92: =_xlfn.IFNA(VLOOKUP($A92,'In-House Hours'!$D$5:$BU$10,6+(COLUMN(C92)-1)*4,FALSE),0) -> 0 | F92: =_xlfn.IFNA(VLOOKUP($A92,'In-House Hours'!$D$5:$BU$10,6+(COLUMN(D92)-1)*4,FALSE),0) -> 0 | G92: =_xlfn.IFNA(VLOOKUP($A92,'In-House Hours'!$D$5:$BU$10,6+(COLUMN(E92)-1)*4,FALSE),0) -> 0 | H92: =_xlfn.IFNA(VLOOKUP($A92,'In-House Hours'!$D$5:$BU$10,6+(COLUMN(F92)-1)*4,FALSE),0) -> 0 | I92: =_xlfn.IFNA(VLOOKUP($A92,'In-House Hours'!$D$5:$BU$10,6+(COLUMN(G92)-1)*4,FALSE),0) -> 0 | J92: =_xlfn.IFNA(VLOOKUP($A92,'In-House Hours'!$D$5:$BU$10,6+(COLUMN(H92)-1)*4,FALSE),0) -> 0 | ... S92: =_xlfn.IFNA(VLOOKUP($A92,'In-House Hours'!$D$5:$BU$10,6+(COLUMN(Q92)-1)*4,FALSE),0) -> 0
A93: C7. Hub Pre-Turning | B93: INR | C93: =_xlfn.IFNA(VLOOKUP($A93,'In-House Hours'!$D$5:$BU$10,6+(COLUMN(A93)-1)*4,FALSE),0) -> 0 | D93: =_xlfn.IFNA(VLOOKUP($A93,'In-House Hours'!$D$5:$BU$10,6+(COLUMN(B93)-1)*4,FALSE),0) -> 0 | E93: =_xlfn.IFNA(VLOOKUP($A93,'In-House Hours'!$D$5:$BU$10,6+(COLUMN(C93)-1)*4,FALSE),0) -> 0 | F93: =_xlfn.IFNA(VLOOKUP($A93,'In-House Hours'!$D$5:$BU$10,6+(COLUMN(D93)-1)*4,FALSE),0) -> 0 | G93: =_xlfn.IFNA(VLOOKUP($A93,'In-House Hours'!$D$5:$BU$10,6+(COLUMN(E93)-1)*4,FALSE),0) -> 0 | H93: =_xlfn.IFNA(VLOOKUP($A93,'In-House Hours'!$D$5:$BU$10,6+(COLUMN(F93)-1)*4,FALSE),0) -> 0 | I93: =_xlfn.IFNA(VLOOKUP($A93,'In-House Hours'!$D$5:$BU$10,6+(COLUMN(G93)-1)*4,FALSE),0) -> 0 | J93: =_xlfn.IFNA(VLOOKUP($A93,'In-House Hours'!$D$5:$BU$10,6+(COLUMN(H93)-1)*4,FALSE),0) -> 0 | ... S93: =_xlfn.IFNA(VLOOKUP($A93,'In-House Hours'!$D$5:$BU$10,6+(COLUMN(Q93)-1)*4,FALSE),0) -> 0
A94: TOTAL IN-HOUSE PROCESSING COST (C) | C94: =SUM(C87:C93) -> 238933.24 | D94: =SUM(D87:D93) -> 238933.24 | E94: =SUM(E87:E93) -> 238933.24 | F94: =SUM(F87:F93) -> 209263.72 | G94: =SUM(G87:G93) -> 238933.24 | H94: =SUM(H87:H93) -> 238933.24 | I94: =SUM(I87:I93) -> 238933.24 | J94: =SUM(J87:J93) -> 238933.24 | ... S94: =SUM(S87:S93) -> 238933.24
A96: SECTION D — OUTSOURCED PROCESSING COST
A97: D1. Machining / Turning Body (Outsourced) | B97: INR | C97: 0 | D97: 0 | E97: 0 | F97: 0 | G97: 0 | H97: 0 | I97: 0 | J97: 0 | K97: 0 | L97: 0 | M97: 0 | N97: 0 | O97: 0 | P97: 0 | Q97: 0 | R97: 0 | S97: 0
A98: D2. Stress Relief Annealing (Outsourced) | B98: INR | C98: 22500 | D98: 22500 | E98: 22500 | F98: 22500 | G98: 22500 | H98: 22500 | I98: 22500 | J98: 22500 | K98: 22500 | L98: 22500 | M98: 22500 | N98: 22500 | O98: 22500 | P98: 22500 | Q98: 22500 | R98: 22500 | S98: 22500
A99: D3. Heat Treatment – Normalising (Outsourced) | B99: INR | C99: 0 | D99: 0 | E99: 0 | F99: 0 | G99: 0 | H99: 0 | I99: 0 | J99: 0 | K99: 0 | L99: 0 | M99: 0 | N99: 0 | O99: 0 | P99: 0 | Q99: 0 | R99: 0 | S99: 0
A100: D4. Painting / Blasting (Outsourced) | B100: INR | C100: 0 | D100: 0 | E100: 0 | F100: 0 | G100: 0 | H100: 0 | I100: 0 | J100: 0 | K100: 0 | L100: 0 | M100: 0 | N100: 0 | O100: 0 | P100: 0 | Q100: 0 | R100: 0 | S100: 0
A101: D5. Lagging Application Labour (Outsourced) | B101: INR | C101: =C52 -> 47506.724 | D101: =D52 -> 42025.179 | E101: =E52 -> 42025.179 | F101: =F52 -> 42025.179 | G101: =G52 -> 53719.142 | H101: =H52 -> 51770.148 | I101: =I52 -> 42634.24 | J101: =J52 -> 41416.119 | ... S101: =S52 -> 47506.724
A102: D6. Dynamic Balancing (Outsourced per set) | B102: INR | C102: ='Cost Rate Tables'!C31 -> 1440 | D102: 0 | E102: 0 | F102: 0 | G102: 0 | H102: 0 | I102: 0 | J102: 0 | K102: 1 | L102: 2 | M102: 3 | N102: 4 | O102: 5 | P102: 6 | Q102: 7 | R102: 8 | S102: 9
A103: D7. Rolling / Bending Shell (Outsourced) | B103: INR | C103: =IF(C60="Outsource",'Cost Rate Tables'!$C$33*C21*0.5,0) -> 0 | D103: =IF(D60="Outsource",'Cost Rate Tables'!$C$33*D21*0.5,0) -> 0 | E103: =IF(E60="Outsource",'Cost Rate Tables'!$C$33*E21*0.5,0) -> 0 | F103: =IF(F60="Outsource",'Cost Rate Tables'!$C$33*F21*0.5,0) -> 0 | G103: =IF(G60="Outsource",'Cost Rate Tables'!$C$33*G21*0.5,0) -> 0 | H103: =IF(H60="Outsource",'Cost Rate Tables'!$C$33*H21*0.5,0) -> 0 | I103: =IF(I60="Outsource",'Cost Rate Tables'!$C$33*I21*0.5,0) -> 0 | J103: =IF(J60="Outsource",'Cost Rate Tables'!$C$33*J21*0.5,0) -> 0 | ... S103: =IF(S60="Outsource",'Cost Rate Tables'!$C$33*S21*0.5,0) -> 0
A104: D8. Shaft Machining (always at specialty vendor) | B104: INR
A105: TOTAL OUTSOURCED PROCESSING COST (D) | C105: =SUM(C97:C104) -> 71446.724 | D105: =SUM(D97:D104) -> 64525.179 | E105: =SUM(E97:E104) -> 64525.179 | F105: =SUM(F97:F104) -> 64525.179 | G105: =SUM(G97:G104) -> 76219.142 | H105: =SUM(H97:H104) -> 74270.148 | I105: =SUM(I97:I104) -> 65134.24 | J105: =SUM(J97:J104) -> 63916.119 | ... S105: =SUM(S97:S104) -> 70015.724
A107: SECTION E — PACKING & SHIPMENT COST
A108: E1. Packing – Wood Crate (per 100 kg) | B108: INR | C108: =C20/100*'Cost Rate Tables'!$C$55 -> 4958.3167 | D108: =D20/100*'Cost Rate Tables'!$C$55 -> 4605.1563 | E108: =E20/100*'Cost Rate Tables'!$C$55 -> 5447.5956 | F108: =F20/100*'Cost Rate Tables'!$C$55 -> 5408.1494 | G108: =G20/100*'Cost Rate Tables'!$C$55 -> 4687.3181 | H108: =H20/100*'Cost Rate Tables'!$C$55 -> 3951.1648 | I108: =I20/100*'Cost Rate Tables'!$C$55 -> 3365.0688 | J108: =J20/100*'Cost Rate Tables'!$C$55 -> 2921.335 | ... S108: =S20/100*'Cost Rate Tables'!$C$55 -> 5420.7815
A109: E2. Inbound Freight – Shaft (per kg) | B109: INR | C109: =C34*'Cost Rate Tables'!$C$52 -> 782.15641 | D109: =D34*'Cost Rate Tables'!$C$52 -> 730.15591 | E109: =E34*'Cost Rate Tables'!$C$52 -> 728.43688 | F109: =F34*'Cost Rate Tables'!$C$52 -> 821.21199 | G109: =G34*'Cost Rate Tables'!$C$52 -> 535.675 | H109: =H34*'Cost Rate Tables'!$C$52 -> 708.7052 | I109: =I34*'Cost Rate Tables'!$C$52 -> 535.675 | J109: =J34*'Cost Rate Tables'!$C$52 -> 708.7052 | ... S109: =S34*'Cost Rate Tables'!$C$52 -> 810.09057
...

Sheet Raw Forging Prices
A1: Shaft with Full Machined Scope | F1: Diameter
B2: Material | C2: diameter | D2: lenght | E2: As-forge/ Kg | F2: Ø 410 lg 3900 | G2: Ø 420-800 lg 2000
B3: C45 | C3: Ø 80 - 180 | D3: 2000 - 3000 | E3: Rs 175 - 225 | F3: 310 | G3: ?
B4: 42CrMo4+QT | C4: Ø 200 - 880 | D4: 2300 - 7300 | E4: Rs 190 - 240 | F4: 330 | G4: ? | J4: Fully M/C
B5: 30CrNiMo8+QT/36CrNiMo4+QT/34CrNiMo6+QT | C5: Ø 300 - 450 | D5: 2300 - 7300 | E5: As per RFQ | F5: Need Basis | G5: ?
A10: Shell
B11: All measurements in [mm]
B12: Diameter Body | C12: Face width Body | D12: Wall Thickness Body --> sheet +x mm | E12: Welded-in plate thickness | F12: T-bottom thickness | G12: Rate /Kg (End Plate) | H12: Rate /Kg (Sheet) | I12: Plate | J12: End Disc(Hub)
A13: Outsoruced | B13: 300 - <=500 | C13: 800-1200 | D13: 10-12 | E13: 50-80 | G13: - | H13: Rs 135-140 | I13: ??? | J13: ???
A14: Inhouse | B14: >550-1000 | C14: 1200-2500 | D14: 15-40 | E14: 50-90 | F14: 100-150 | G14: Rs 195 - 210 | H14: Rs 95-110 | I14: 110 | J14: 210
A15: Inhouse | B15: 1000-1500 | C15: 1500-2500 | D15: 20-40 | F15: 100-200 | G15: Rs 195 - 210 | H15: Rs 95-110 | I15: 110 | J15: 210
A16: Inhouse | B16: 1500-2000 | C16: 1500-2500 | D16: 20-40 | F16: 100-200 | G16: Rs 195 - 210 | H16: Rs 135 - 145 | I16: 130 | J16: 210
A17: Inhouse | B17: >2000 | C17: 1500-2500 | D17: 20-40 | F17: 100-200 | H17: As per RFQ | J17: 210

Sheet TECH DATA SHEET
A1: PULLEY — PRICING TOOL INPUT DATA SHEET (VTIP)
A2: Customer Name : | B2: NMDC
A3: Final Destination: | B3: Lima - Peru | F3: Payment Terms | G3: Ex Works Hyderabad | H3: Incoterms | I3: Ex Works Hyderabad | K3: Date: | L3: 46196
A4: Techinical Data: | B4: Mr.Adam | F4: Delivery Time: | G4: 18 Weeks | H4: Version: | I4: Ver-1
A5: PARAMETER | B5: Unit | C5: MODEL 1 Pulley | D5: MODEL 2 Pulley | E5: MODEL 3 Pulley | F5: MODEL 4 Pulley | G5: MODEL 5 Pulley | H5: MODEL 6 Pulley | I5: MODEL 7 Pulley | J5: MODEL 8 Pulley | K5: MODEL 9 Pulley | L5: MODEL 10 Pulley | M5: MODEL 11 Pulley | N5: MODEL 12 Pulley | O5: MODEL 13 Pulley | P5: MODEL 14 Pulley | Q5: MODEL 15 Pulley | R5: MODEL 16 Pulley | S5: MODEL 17 Pulley
A6: 1. PROJECT INFORMATION
A7: Project / Quote Reference | B7: — | C7: P0108789-Pulleys for -01352532 | D7: P0108789-Pulleys for -01352532 | E7: P0108789-Pulleys for -01352532 | F7: P0108789-Pulleys for -01352532 | G7: P0108789-Pulleys for -01352532 | H7: P0108789-Pulleys for -01352532 | I7: P0108789-Pulleys for -01352532 | J7: P0108789-Pulleys for -01352532 | K7: P0108789-Pulleys for -01352532 | L7: P0108789-Pulleys for -01352532 | M7: P0108789-Pulleys for -01352532 | N7: P0108789-Pulleys for -01352532 | O7: P0108789-Pulleys for -01352532 | P7: P0108789-Pulleys for -01352532 | Q7: P0108789-Pulleys for -01352532 | R7: P0108789-Pulleys for -01352532 | S7: P0108789-Pulleys for -01352532
A8: Pulley Tag / Name | B8: — | C8: pulley_1 | D8: pulley_2 | E8: pulley_3 | F8: pulley_4 | G8: pulley_5 | H8: pulley_6 | I8: pulley_7 | J8: pulley_8 | K8: pulley_9 | L8: pulley_10 | M8: pulley_11 | N8: pulley_12 | O8: pulley_13 | P8: pulley_14 | Q8: pulley_15 | R8: pulley_16 | S8: pulley_17
A9: Pulley Structure | B9: — | C9: live shaft pulley | D9: live shaft pulley | E9: live shaft pulley | F9: live shaft pulley | G9: live shaft pulley | H9: live shaft pulley | I9: live shaft pulley | J9: live shaft pulley | K9: live shaft pulley | L9: live shaft pulley | M9: live shaft pulley | N9: live shaft pulley | O9: live shaft pulley | P9: live shaft pulley | Q9: live shaft pulley | R9: live shaft pulley | S9: live shaft pulley
A10: Number of Pulleys (qty) | B10: nos | C10: 2 | D10: 3 | E10: 2 | F10: 1 | G10: 2 | H10: 2 | I10: 4 | J10: 3 | K10: 7 | L10: 6 | M10: 2 | N10: 3 | O10: 8 | P10: 3 | Q10: 6 | R10: 1 | S10: 1
A12: 2. PULLEY BODY DIMENSIONS
A13: Shell Outer Diameter Dshell | B13: mm | C13: 600 | D13: 600 | E13: 600 | F13: 600 | G13: 630 | H13: 500 | I13: 500 | J13: 400 | K13: 400 | L13: 400 | M13: 500 | N13: 630 | O13: 400 | P13: 500 | Q13: 630 | R13: 800 | S13: 650
A14: Shell Face Width Lface | B14: mm | C14: 1300 | D14: 1150 | E14: 1150 | F14: 1150 | G14: 1400 | H14: 1700 | I14: 1400 | J14: 1700 | K14: 1400 | L14: 1400 | M14: 1400 | N14: 1200 | O14: 1200 | P14: 1200 | Q14: 1200 | R14: 1200 | S14: 1200
A15: Shell Thickness | B15: mm | C15: 22 | D15: 22 | E15: 32 | F15: 32 | G15: 22 | H15: 22 | I15: 22 | J15: 22 | K15: 22 | L15: 22 | M15: 22 | N15: 22 | O15: 22 | P15: 22 | Q15: 22 | R15: 22 | S15: 22
A16: Sheet Width | B16: mm | C16: =C14 -> 1300 | D16: =D14 -> 1150 | E16: =E14 -> 1150 | F16: =F14 -> 1150 | G16: =G14 -> 1400 | H16: =H14 -> 1700 | I16: =I14 -> 1400 | J16: =J14 -> 1700 | ... S16: =S14 -> 1200
A17: Sheet Length | B17: mm | C17: =(C13+8-C15)*3.141593+100 -> 1940.9735 | D17: =(D13+8-D15)*3.141593+100 -> 1940.9735 | E17: =(E13+8-E15)*3.141593+100 -> 1909.5576 | F17: =(F13+8-F15)*3.141593+100 -> 1909.5576 | G17: =(G13+8-G15)*3.141593+100 -> 2035.2213 | H17: =(H13+8-H15)*3.141593+100 -> 1626.8142 | I17: =(I13+8-I15)*3.141593+100 -> 1626.8142 | J17: =(J13+8-J15)*3.141593+100 -> 1312.6549 | ... S17: =(S13+8-S15)*3.141593+100 -> 2098.0531
A18: Overall Pulley Diameter with Lagging | B18: mm | C18: 624 | D18: 624 | E18: 624 | F18: 624 | G18: 654 | H18: 524 | I18: 524 | J18: 424 | K18: 424 | L18: 424 | M18: 524 | N18: 654 | O18: 424 | P18: 524 | Q18: 654 | R18: 824 | S18: 674
A19: Bearing Housing Distance L1 | B19: mm | C19: 1650 | D19: 1525 | E19: 1525 | F19: 1525 | G19: 1665 | H19: 1955 | I19: 1665 | J19: 1955 | K19: 1665 | L19: 1620 | M19: 1640 | N19: 1465 | O19: 1420 | P19: 1440 | Q19: 1465 | R19: 1465 | S19: 1465
A20: Total Pulley Mass mtotal | B20: kg | C20: 762.81795 | D20: 708.48558 | E20: 838.09164 | F20: 832.02298 | G20: 721.12586 | H20: 607.87151 | I20: 517.70289 | J20: 449.43615 | K20: 377.76366 | L20: 382.89818 | M20: 511.69878 | O20: 335.11652 | P20: 451.58637 | Q20: 644.98347 | R20: 1201.5828 | S20: 833.96638
A21: Sheel Plate Weight (Kg) | B21: kg | C21: =(C15*(C16/1000)*(C17/1000)*7.85) -> 435.76796 | D21: =(D15*(D16/1000)*(D17/1000)*7.85) -> 385.48704 | E21: =(E15*(E16/1000)*(E17/1000)*7.85) -> 551.63299 | F21: =(F15*(F16/1000)*(F17/1000)*7.85) -> 551.63299 | G21: =(G15*(G16/1000)*(G17/1000)*7.85) -> 492.0758 | H21: =(H15*(H16/1000)*(H17/1000)*7.85) -> 477.61638 | I21: =(I15*(I16/1000)*(I17/1000)*7.85) -> 393.33114 | J21: =(J15*(J16/1000)*(J17/1000)*7.85) -> 385.38235 | ... S21: =(S15*(S16/1000)*(S17/1000)*7.85) -> 434.80053
A22: Shell Rate Per Kg | B22: kg | C22: 136
A23: 3. HUB SPECIFICATIONS
A24: Hub Type | B24: — | C24: Profiled T/C-hub | D24: Profiled T/C-hub | E24: Profiled T/C-hub | F24: Profiled T/C-hub | G24: welded in solid hub | H24: welded in solid hub | I24: welded in solid hub | J24: welded in solid hub | K24: welded in solid hub | L24: welded in solid hub | M24: welded in solid hub | N24: welded in solid hub | O24: welded in welded hub | P24: welded in solid hub | Q24: welded in solid hub | R24: Profiled T/C-hub | S24: Profiled T/C-hub
A25: Hub Width Whub | B25: mm | C25: 124 | D25: 124 | E25: 124 | F25: 124 | G25: 90 | H25: 90 | I25: 90 | J25: 90 | K25: 90 | L25: 78 | M25: 78 | N25: 78 | O25: 78 | P25: 78 | Q25: 90 | R25: 127 | S25: 124
A26: Min. Outer Diameter of Hub DN | B26: mm | C26: 395 | D26: 395 | E26: 395 | F26: 405 | G26: 335 | H26: 335 | I26: 335 | J26: 335 | K26: 335 | L26: 250 | M26: 265 | N26: 265 | O26: 250 | P26: 265 | Q26: 335 | R26: 405 | S26: 395
A27: Hub Inner Diameter d_LD (= LD bore) | B27: mm | C27: 240 | D27: 240 | E27: 240 | F27: 250 | G27: 200 | H27: 200 | I27: 200 | J27: 200 | K27: 200 | L27: 150 | M27: 170 | N27: 170 | O27: 150 | P27: 170 | Q27: 200 | R27: 250 | S27: 240
A28: Hub Mass (est., 2 hubs) [auto] | B28: kg | C28: =2*PI()/4*((C26/1000)^2-(C27/1000)^2)*(C25/1000)*7850 -> 150.49312 | D28: =2*PI()/4*((D26/1000)^2-(D27/1000)^2)*(D25/1000)*7850 -> 150.49312 | E28: =2*PI()/4*((E26/1000)^2-(E27/1000)^2)*(E25/1000)*7850 -> 150.49312 | F28: =2*PI()/4*((F26/1000)^2-(F27/1000)^2)*(F25/1000)*7850 -> 155.23306 | G28: =2*PI()/4*((G26/1000)^2-(G27/1000)^2)*(G25/1000)*7850 -> 80.152965 | H28: =2*PI()/4*((H26/1000)^2-(H27/1000)^2)*(H25/1000)*7850 -> 80.152965 | I28: =2*PI()/4*((I26/1000)^2-(I27/1000)^2)*(I25/1000)*7850 -> 80.152965 | J28: =2*PI()/4*((J26/1000)^2-(J27/1000)^2)*(J25/1000)*7850 -> 80.152965 | ... S28: =2*PI()/4*((S26/1000)^2-(S27/1000)^2)*(S25/1000)*7850 -> 150.49312
A29: End Disk Per Kg | B29: kg
A30: 4. SHAFT SPECIFICATIONS
A31: Shaft Total Length Lshaft | B31: mm | C31: 1820 | D31: 1699 | E31: 1695 | F31: 1713 | G31: 1803 | H31: 2093 | I31: 1803 | J31: 2093 | K31: 1803 | L31: 1710 | M31: 1748 | N31: 1869 | O31: 1510 | P31: 1548 | Q31: 1603 | R31: 1653 | S31: 1885
A32: Shaft Centre Diameter d4 | B32: mm | C32: 178 | D32: 178 | E32: 178 | F32: 188 | G32: 148 | H32: 158 | I32: 148 | J32: 158 | K32: 148 | L32: 118 | M32: 138 | N32: 158 | O32: 118 | P32: 128 | Q32: 148 | R32: 188 | S32: 178
A33: Shaft Material | B33: — | C33: 42CrMo4+QT | D33: 42CrMo4+QT | E33: 42CrMo4+QT | F33: 42CrMo4+QT | G33: 42CrMo4+QT | H33: 42CrMo4+QT | I33: 42CrMo4+QT | J33: 42CrMo4+QT | K33: 42CrMo4+QT | L33: 42CrMo4+QT | M33: 42CrMo4+QT | N33: 42CrMo4+QT | O33: 42CrMo4+QT | P33: 42CrMo4+QT | Q33: 42CrMo4+QT | R33: 42CrMo4+QT | S33: 42CrMo4+QT
A34: Shaft Mass [auto-calculated] | B34: kg | C34: =PI()/4*(C32/1000)^2*C31/1000*7850 -> 355.52564 | D34: =PI()/4*(D32/1000)^2*D31/1000*7850 -> 331.88905 | E34: =PI()/4*(E32/1000)^2*E31/1000*7850 -> 331.10767 | F34: =PI()/4*(F32/1000)^2*F31/1000*7850 -> 373.27818 | G34: =PI()/4*(G32/1000)^2*G31/1000*7850 -> 243.48864 | H34: =PI()/4*(H32/1000)^2*H31/1000*7850 -> 322.13873 | I34: =PI()/4*(I32/1000)^2*I31/1000*7850 -> 243.48864 | J34: =PI()/4*(J32/1000)^2*J31/1000*7850 -> 322.13873 | ... S34: =PI()/4*(S32/1000)^2*S31/1000*7850 -> 368.22299
A35: Shaft Per Kg | B35: kg
A36: 5. BEARINGS, HOUSINGS & SLEEVES
A37: Bearing 1 Designation | B37: — | C37: 22232 CCK/W33 | D37: 22234 CCK/W33 | E37: 22232 CCK/W33 | F37: 22236 CCK/W33 | G37: 22228 CCK/W33 | H37: 22228 CCK/W33 | I37: 22228 CCK/W33 | J37: 22228 CCK/W33 | K37: 22228 CCK/W33 | L37: 22218 EK | M37: 22222 EK | N37: 22228 CCK/W33 | O37: 22218 EK | P37: 22222 EK | Q37: 22228 CCK/W33 | R37: 23136 CCK/W33 | S37: 22232 CCK/W33
A39: Bearing 2 Designation | B39: — | C39: =C37 -> 22232 CCK/W33 | D39: =D37 -> 22234 CCK/W33 | E39: =E37 -> 22232 CCK/W33 | F39: =F37 -> 22236 CCK/W33 | G39: =G37 -> 22228 CCK/W33 | H39: =H37 -> 22228 CCK/W33 | I39: =I37 -> 22228 CCK/W33 | J39: =J37 -> 22228 CCK/W33 | ... S39: =S37 -> 22232 CCK/W33
A41: Adapter Sleeve Code | B41: — | C41: H 3132 | D41: H 3134 | E41: H 3132 | F41: H 3136 | G41: H 3128 | H41: H 3128 | I41: H 3128 | J41: H 3128 | K41: H 3128 | L41: H 318 | M41: H 322 | N41: H 3128 | O41: H 318 | P41: H 322 | Q41: H 3128 | R41: H 3136 | S41: H 3132
A43: Housing Designation | B43: — | C43: SNL 532 | D43: SNL 3234 | E43: SNL 532 | F43: SNL 3138 | G43: SNL 528 | H43: SNL 528 | I43: SNL 528 | J43: SNL 528 | K43: SNL 528 | L43: SNL 518-615 | M43: SNL 522-619 | N43: SNL 528 | O43: SNL 518-615 | P43: SNL 522-619 | Q43: SNL 528 | R43: SNL 3136 | S43: SNL532
A45: Total Bearings + Sleeves + Housings (2× each) | B45: INR | C45: =2*(C38+C40+C42+C44) -> 0 | D45: =2*(D38+D40+D42+D44) -> 0 | E45: =2*(E38+E40+E42+E44) -> 0 | F45: =2*(F38+F40+F42+F44) -> 0 | G45: =2*(G38+G40+G42+G44) -> 0 | H45: =2*(H38+H40+H42+H44) -> 0 | I45: =2*(I38+I40+I42+I44) -> 0 | J45: =2*(J38+J40+J42+J44) -> 0 | ... L45: =2*(L38+L40+L42+L44) -> 0
A47: 6. LAGGING
A48: Lagging Type | B48: — | C48: Rubber vulc. 12mm | D48: Rubber vulc. 12mm | E48: Rubber vulc. 12mm | F48: Rubber vulc. 12mm | G48: Rubber vulc. 12mm | H48: Rubber vulc. 12mm | I48: Rubber vulc. 12mm | J48: Rubber vulc. 12mm | K48: Rubber vulc. 12mm | L48: Rubber vulc. 12mm | M48: Rubber vulc. 12mm | N48: Rubber vulc. 12mm | O48: Rubber vulc. 12mm | P48: Rubber vulc. 12mm | Q48: Rubber vulc. 12mm | R48: Rubber vulc. 12mm | S48: Rubber vulc. 12mm
A49: Lagging Thickness | B49: mm | C49: 12 | D49: 12 | E49: 12 | F49: 12 | G49: 12 | H49: 12 | I49: 12 | J49: 12 | K49: 12 | L49: 12 | M49: 12 | N49: 12 | O49: 12 | P49: 12 | Q49: 12 | R49: 12 | S49: 12
A50: Lagging Area [auto: π × Dshell × Lface] | B50: m² | C50: =PI()*C13/1000*C14/1000 -> 2.4504423 | D50: =PI()*D13/1000*D14/1000 -> 2.1676989 | E50: =PI()*E13/1000*E14/1000 -> 2.1676989 | F50: =PI()*F13/1000*F14/1000 -> 2.1676989 | G50: =PI()*G13/1000*G14/1000 -> 2.7708847 | H50: =PI()*H13/1000*H14/1000 -> 2.6703538 | I50: =PI()*I13/1000*I14/1000 -> 2.1991149 | J50: =PI()*J13/1000*J14/1000 -> 2.136283 | ... S50: =PI()*S13/1000*S14/1000 -> 2.4504423
A52: Lagging Cost [auto] | B52: INR | C52: =C50*C51 -> 0 | D52: =D50*D51 -> 0 | E52: =E50*E51 -> 0 | F52: =F50*F51 -> 0 | G52: =G50*G51 -> 0 | H52: =H50*H51 -> 0 | I52: =I50*I51 -> 0 | J52: =J50*J51 -> 0 | ... S52: =S50*S51 -> 0
A54: 7. LOCKING DEVICE & DEAD SHAFT PARTS
A55: Locking Device Type | B55: — | C55: NMTG N7036-170 × 240 | D55: NMTG N7036-170 × 240 | E55: NMTG N7036-170 × 240 | F55: NMTG N7036-180 × 250 | G55: NMTG N7036-140 × 200 | H55: NMTG N7036-140 × 200 | I55: NMTG N7036-140 × 200 | J55: NMTG N7036-140 × 200 | K55: NMTG N7036-140 × 200 | L55: NMTG N7036-100 × 150 | M55: NMTG N7036-120 × 170 | N55: NMTG N7036-150 x 210 | O55: NMTG N7036-100 × 150 | P55: NMTG N7036-120 × 170 | Q55: NMTG N7036-140 × 200 | R55: NMTG N7036-180 × 250 | S55: NMTG N7036-170 × 240
A56: Locking Device INR Price | B56: INR
A57: Dead Shaft Parts (inner tube, supports, seals) | B57: INR | C57: 0 | D57: 0 | E57: 0 | F57: 0 | G57: 0 | H57: 0 | I57: 0 | J57: 0

Sheet Cost Rate Tables
B1: COST RATE TABLES — INDIA OPERATIONS | Update all yellow cells here
B3: A. GLOBAL PARAMETERS
B4: Parameter | C4: Value | D4: Unit | E4: Notes
B5: Exchange Rate EUR → INR | C5: 110 | D5: INR/EUR | E5: Update on calculation date
B6: GST Rate | C6: 0.18 | D6: % | E6: Standard 18% GST
B7: OEM Discount | C7: 0.1 | D7: % | E7: Standard OEM 10%
B8: Price Factor HK0 (markup) | C8: 1.8 | D8: × | E8: Applied to direct cost → list price
B9: Delivery Safety Factor | C9: 1.2 | D9: × | E9: Buffer on base delivery
B11: B. MATERIAL RATES (INR/kg)
B12: Material | C12: INR/kg | D12: EUR/kg | E12: Notes
B13: Disc plate IS 2062 E350 | C13: =73030/544 -> 134.24632 | D13: =C13/'Cost Rate Tables'!C5 -> 1.2204211
B14: Shell plate IS 2062 E350 | C14: =62480/763 -> 81.887287 | D14: =C14/'Cost Rate Tables'!C5 -> 0.74442988
B15: Shaft – C45 round bar | C15: 91 | D15: =C15/'Cost Rate Tables'!C5 -> 0.82727273
B16: Shaft – 42CrMo4 alloy steel forged | C16: =310000/1325 -> 233.96226 | D16: =C16/'Cost Rate Tables'!C5 -> 2.1269297 | E16: Mat+Machining
B17: Weld consumables (per kg pulley) | C17: 6 | D17: =C17/'Cost Rate Tables'!C5 -> 0.054545455
B18: Grease | C18: 18 | D18: =C18/'Cost Rate Tables'!C5 -> 0.16363636
B21: C. MACHINING & LABOUR RATES (INR/hour)
B22: Operation | C22: INR/h | D22: EUR/h | E22: Sourcing Default
B23: Lathe turning | C23: ='MHR & LHR Calculator'!D55 -> 711.26667 | D23: =C23/'Cost Rate Tables'!C5 -> 6.4660606 | E23: ← Auto from MHR & LHR Calculator
B24: Rolling / bending | C24: ='MHR & LHR Calculator'!E55 -> 893.34524 | D24: =C24/'Cost Rate Tables'!C5 -> 8.1213203 | E24: ← Auto from MHR & LHR Calculator
B25: Welding (MIG/MAG) | C25: ='MHR & LHR Calculator'!F55 -> 497.86458 | D25: =C25/'Cost Rate Tables'!C5 -> 4.5260417 | E25: ← Auto from MHR & LHR Calculator
B26: Grinding / finishing | C26: ='MHR & LHR Calculator'!G55 -> 491.31548 | D26: =C26/'Cost Rate Tables'!C5 -> 4.4665043 | E26: ← Auto from MHR & LHR Calculator
B27: Assembly labour | C27: ='MHR & LHR Calculator'!H55 -> 911.8254 | D27: =C27/'Cost Rate Tables'!C5 -> 8.2893218 | E27: ← Auto from MHR & LHR Calculator
B28: Engineering / design | C28: ='MHR & LHR Calculator'!J55 -> 338.11765 | D28: =C28/'Cost Rate Tables'!C5 -> 3.0737968 | E28: ← Auto from MHR & LHR Calculator
B29: Heat treatment / annealing (per kg) | C29: 8.5 | D29: =C29/'Cost Rate Tables'!C5 -> 0.077272727 | E29: Outsource
B30: Stress relief (per kg) | C30: 7.2 | D30: =C30/'Cost Rate Tables'!C5 -> 0.065454545 | E30: Outsource | F30: Get the Table for rates
B31: Balancing (per set) | C31: 1440 | D31: =C31/'Cost Rate Tables'!C5 -> 13.090909 | E31: In-house
B32: Painting / surface prep (per m²) | C32: ='MHR & LHR Calculator'!I55 -> 924.9989 | D32: =C32/'Cost Rate Tables'!C5 -> 8.4090809 | E32: ← Auto from MHR & LHR Calculator
B33: Machining body – outsourced (per kg) | C33: =125000/1434 -> 87.168759 | D33: =C33/'Cost Rate Tables'!C5 -> 0.79244326 | E33: Outsource | F33: Get the Table for rates
B36: D. LAGGING RATES (INR/m² — India price list Jan 2026)
B37: Lagging Type | C37: Thickness mm | D37: INR/m² | E37: Lead Time (days)
B38: Rubber hot vulcanized | C38: 12 | D38: 19387 | E38: 14
B39: Rubber hot vulcanized | C39: 15 | D39: 20702 | E39: 14
B40: Rubber hot vulcanized | C40: 20 | D40: 22439 | E40: 14
B41: Rubber hot vulcanized | C41: 25 | D41: 24222 | E41: 14
B42: Rubber hot vulcanized | C42: 30 | D42: 26241 | E42: 14
B43: Rubber ceramic | C43: 15 | D43: 27344 | E43: 14
B44: Rubber ceramic | C44: 20 | D44: 29574 | E44: 14
B45: Rubber ceramic | C45: 25 | D45: 31828 | E45: 14
B46: Full ceramic | C46: 6 | D46: 148661 | E46: 7
B47: Full ceramic | C47: 10 | D47: 193950 | E47: 7
B48: No lagging | C48: 0 | D48: 0 | E48: 0
B50: E. LOGISTICS & PACKING RATES
B51: Item | C51: Rate | D51: Unit | E51: Notes
B52: Inbound freight – shaft (per kg) | C52: 2.2 | D52: INR/kg
B53: Inbound freight – plates (per kg) | C53: 1.8 | D53: INR/kg
B54: Inbound freight – purchased parts (per order) | C54: 1500 | D54: INR/order
B55: Packing – wood crate (per 100 kg) | C55: 650 | D55: INR/100kg
B56: Outbound shipping FOB (per kg) | C56: 3.5 | D56: INR/kg

Sheet Bearing & Sleeve Data
B1: BEARING, SLEEVE & HOUSING DATA — INDIA SOURCING | Reference for Pricing Calculator
B3: A. SPHERICAL ROLLER BEARINGS — INDIA PRICES (SKF/FAG)
B4: Designation | C4: Bore d (mm) | D4: INR Price (ea) | E4: EUR Price (ea) | F4: Delivery (days) | G4: Make / Brand | H4: Series
B5: 22218 EK | C5: 90 | D5: 10234 | E5: 93.1 | F5: 60 | G5: SKF/FAG | H5: 22200
B6: 22219 EK | C6: 95 | D6: 7383 | E6: 67.2 | F6: 60 | G6: SKF/FAG | H6: 22200
B7: 22220 EK | C7: 100 | D7: 6900 | E7: 62.8 | F7: 60 | G7: SKF/FAG | H7: 22200
B8: 22222 EK | C8: 110 | D8: 7356 | E8: 66.9 | F8: 60 | G8: SKF/FAG | H8: 22200
B9: 22224 EK | C9: 120 | D9: 9477 | E9: 86.2 | F9: 60 | G9: SKF/FAG | H9: 22200
B10: 22226 EK | C10: 130 | D10: 30249 | E10: 275.3 | F10: 60 | G10: SKF/FAG | H10: 22200
B11: 22228 CCK/W33 | C11: 140 | D11: 23593 | E11: 214.7 | F11: 60 | G11: SKF/FAG | H11: 22200
B12: 22232 KEM | C12: 160 | D12: 28616 | E12: 260.4 | F12: 60 | G12: SKF/FAG | H12: 22200
B13: 22244 CCK/W33 | C13: 220 | D13: 84013 | E13: 764.5 | F13: 60 | G13: SKF/FAG | H13: 22200
B14: 23044 CCK/W33 | C14: 220 | D14: 54559 | E14: 496.5 | F14: 60 | G14: SKF/FAG | H14: 23000
B15: 23048 CCK/W33 | C15: 240 | E15: 932.1 | F15: 60 | G15: SKF/FAG | H15: 23000
B16: 23052 CCK/W33 | C16: 260 | D16: 75525 | E16: 687.3 | F16: 60 | G16: SKF/FAG | H16: 23000
B17: 23132 CCK/W33 | C17: 160 | D17: 33826 | E17: 307.8 | F17: 60 | G17: SKF/FAG | H17: 23100
B18: 23134 CCK/W33 | C18: 170 | D18: 35456 | E18: 322.6 | F18: 60 | G18: SKF/FAG | H18: 23100
B19: 23136 CCK/W33 | C19: 180 | D19: 64900 | E19: 590.6 | F19: 60 | G19: SKF/FAG | H19: 23100
B20: 23138 CCK/W33 | C20: 190 | D20: 67016 | E20: 609.8 | F20: 60 | G20: SKF/FAG | H20: 23100
B21: 23144 CCK/W33 | C21: 220 | D21: 74531 | E21: 678.2 | F21: 60 | G21: SKF/FAG | H21: 23100
B22: 23148 CCK/W33 | C22: 240 | D22: 87609 | E22: 797.2 | F22: 60 | G22: SKF/FAG | H22: 23100
B23: 23152 CCK/W33 | C23: 260 | D23: 150761 | E23: 1371.9 | F23: 60 | G23: SKF/FAG | H23: 23100
B24: 23160 CCK/W33 | C24: 300 | D24: 197823 | E24: 1800.2 | F24: 60 | G24: SKF/FAG | H24: 23100
B25: 23164 CCK/W33 | C25: 320 | D25: 185965 | E25: 1692.3 | F25: 90 | G25: SKF/FAG | H25: 23100
B26: 23168 CCK/W33 | C26: 340 | D26: 215156 | E26: 1957.9 | F26: 90 | G26: SKF/FAG | H26: 23100
B27: 23176 CAK/W33 | C27: 380 | E27: 4151.7 | F27: 90 | G27: SKF/FAG | H27: 23100
B28: 23180 CAK/W33 | C28: 400 | E28: 4268.3 | F28: 120 | G28: SKF/FAG | H28: 23100
B29: 23184 CKJ/W33 | C29: 420 | E29: 5303.3 | F29: 120 | G29: SKF/FAG | H29: 23100
B30: 23188 CAK/W33 | C30: 440 | E30: 6597.7 | F30: 120 | G30: SKF/FAG | H30: 23100
B31: 23192 CAK/W33 | C31: 460 | E31: 6545.7 | F31: 120 | G31: SKF/FAG | H31: 23100
B32: 23196 CAK/W33 | C32: 480 | E32: 8401.4 | F32: 120 | G32: SKF/FAG | H32: 23100
B33: 24132 CCK30/W33 | C33: 160 | E33: 370.8 | F33: 60 | G33: SKF/FAG | H33: 24100
B34: 24140 CCK/C3W33 | C34: 200 | E34: 787.8 | F34: 60 | G34: SKF/FAG | H34: 24100
B35: 24144 CCK30/W33 | C35: 220 | E35: 879.9 | F35: 60 | G35: SKF/FAG | H35: 24100
B36: 24160 CCK/W33 | C36: 300 | E36: 2484.5 | F36: 60 | G36: SKF/FAG | H36: 24100
B37: 24172 ECCK30J/W33 | C37: 360 | E37: 5200.1 | F37: 90 | G37: SKF/FAG | H37: 24100
B38: 24180 ECAK30/W33 | C38: 400 | E38: 6634.2 | F38: 120 | G38: SKF/FAG | H38: 24100
B41: B. ADAPTER SLEEVES — INDIA PRICES
B42: Sleeve Code | C42: For Bearing | D42: EUR Price (ea) | E42: INR Price (ea) | F42: Delivery (days) | G42: Make / Brand
B43: H 318 | C43: 22218 | D43: 13 | E43: 1428 | F43: 30 | G43: SKF
B44: H 319 | C44: 22219 | D44: 17.8 | F44: 30 | G44: SKF
B45: H 320 | C45: 22220 | D45: 20.2 | F45: 30 | G45: SKF
B46: H 322 | C46: 22222 | D46: 13.3 | E46: 1463 | F46: 30 | G46: SKF
B47: H 3124 | C47: 22224 | D47: 28.9 | F47: 30 | G47: SKF
B48: H 3126 | C48: 22226 | D48: 28.9 | E48: 3181 | F48: 30 | G48: SKF
B49: H 3128 | C49: 22228 | D49: 52.9 | F49: 30 | G49: SKF
B50: H 3132 | C50: 22232 | D50: 45.4 | E50: 4988 | F50: 30 | G50: SKF
B51: OH 3136 H | C51: 22236 | E51: 13800 | F51: 30 | G51: SKF
B52: OH 3044 H | C52: 23044 | D52: 303.1 | F52: 75 | G52: SKF
B53: OH 3048 H | C53: 23048 | D53: 498.3 | F53: 75 | G53: SKF
B54: OH 3052 H | C54: 23052 | D54: 463.9 | F54: 75 | G54: SKF
B55: OH 3060 H | C55: 23060 | D55: 678.3 | F55: 75 | G55: SKF
B56: OH 3064 H | C56: 23064 | D56: 596.7 | F56: 75 | G56: SKF
B57: H 3136 | C57: 23136 | E57: 13800 | F57: 30 | G57: SKF
B58: OH 3144 H | C58: 23144 | F58: 75 | G58: SKF
B59: OH 3160 H | C59: 23160 | D59: 534.2 | F59: 75 | G59: SKF
B60: H 3164 | C60: 23164 | F60: 75 | G60: SKF

Sheet In-House Hours
A1: IN-HOUSE PROCESSING — OPERATION HOURS & COST BY MODEL
A2: Links to MHR & LHR Calculator → rates auto-update. Enter Run Time (min) and Setup Time (min) per operation per model.
F3: ='Pricing Tool'!C5 -> MODEL 1 | J3: ='Pricing Tool'!D5 -> MODEL 2 | N3: ='Pricing Tool'!E5 -> MODEL 3 | R3: ='Pricing Tool'!F5 -> MODEL 4 | V3: ='Pricing Tool'!G5 -> MODEL 5 | Z3: ='Pricing Tool'!H5 -> MODEL 6 | AD3: ='Pricing Tool'!I5 -> MODEL 7 | AH3: ='Pricing Tool'!J5 -> MODEL 8 | AL3: ='Pricing Tool'!K5 -> MODEL 9 | AP3: ='Pricing Tool'!L5 -> MODEL 10 | AT3: ='Pricing Tool'!M5 -> MODEL 11 | AX3: ='Pricing Tool'!N5 -> MODEL 12 | BB3: ='Pricing Tool'!O5 -> MODEL 13 | BF3: ='Pricing Tool'!P5 -> MODEL 14 | BJ3: ='Pricing Tool'!Q5 -> MODEL 15 | BN3: ='Pricing Tool'!R5 -> MODEL 16 | BR3: ='Pricing Tool'!S5 -> MODEL 17
A4: Cost Head | B4: Operation | C4: Cost Centre | D4: Activity Description | E4: MHR Rate (INR/hr) | F4: Run (min) | G4: Setup (min) | H4: Total Hours | I4: Cost (INR) | J4: Run (min) | K4: Setup (min) | L4: Total Hours | M4: Cost (INR) | N4: Run (min) | O4: Setup (min) | P4: Total Hours | Q4: Cost (INR) | R4: Run (min) | S4: Setup (min) | T4: Total Hours | U4: Cost (INR) | V4: Run (min) | W4: Setup (min) | X4: Total Hours | Y4: Cost (INR) | Z4: Run (min) | AA4: Setup (min) | AB4: Total Hours | AC4: Cost (INR) | AD4: Run (min) | AE4: Setup (min) | AF4: Total Hours | AG4: Cost (INR) | AH4: Run (min) | AI4: Setup (min) | AJ4: Total Hours | AK4: Cost (INR) | AL4: Run (min) | AM4: Setup (min) | AN4: Total Hours | AO4: Cost (INR) | AP4: Run (min) | AQ4: Setup (min) | AR4: Total Hours | AS4: Cost (INR) | AT4: Run (min) | AU4: Setup (min) | AV4: Total Hours | AW4: Cost (INR) | AX4: Run (min) | AY4: Setup (min) | AZ4: Total Hours | BA4: Cost (INR) | BB4: Run (min) | BC4: Setup (min) | BD4: Total Hours | BE4: Cost (INR) | BF4: Run (min) | BG4: Setup (min) | BH4: Total Hours | BI4: Cost (INR) | BJ4: Run (min) | BK4: Setup (min) | BL4: Total Hours | BM4: Cost (INR) | BN4: Run (min) | BO4: Setup (min) | BP4: Total Hours | BQ4: Cost (INR) | BR4: Run (min) | BS4: Setup (min) | BT4: Total Hours | BU4: Cost (INR)
A5: 10c. Welding – Shell & Hub | B5: Welding (MIG/MAG) Grinding / finishing | D5: C2. Welding – Shell & Hub | E5: 24.520266 | F5: 3210 | G5: 930 | H5: =F5+G5 -> 4140 | I5: =$E5*H5 -> 101513.9 | J5: 3210 | K5: 930 | L5: =J5+K5 -> 4140 | M5: =$E5*L5 -> 101513.9 | N5: 3210 | O5: 930 | P5: =N5+O5 -> 4140 | Q5: =$E5*P5 -> 101513.9 | R5: 2000 | S5: 930 | T5: =R5+S5 -> 2930 | U5: =$E5*T5 -> 71844.381 | V5: 3210 | W5: 930 | X5: =V5+W5 -> 4140 | Y5: =$E5*X5 -> 101513.9 | Z5: 3210 | AA5: 930 | AB5: =Z5+AA5 -> 4140 | AC5: =$E5*AB5 -> 101513.9 | AD5: 3210 | AE5: 930 | AF5: =AD5+AE5 -> 4140 | AG5: =$E5*AF5 -> 101513.9 | AH5: 3210 | AI5: 930 | AJ5: =AH5+AI5 -> 4140 | AK5: =$E5*AJ5 -> 101513.9 | AL5: 3210 | AM5: 930 | AN5: =AL5+AM5 -> 4140 | AO5: =$E5*AN5 -> 101513.9 | AP5: 3210 | AQ5: 930 | AR5: =AP5+AQ5 -> 4140 | AS5: =$E5*AR5 -> 101513.9 | AT5: 3210 | AU5: 930 | AV5: =AT5+AU5 -> 4140 | AW5: =$E5*AV5 -> 101513.9 | AX5: 3210 | AY5: 930 | AZ5: =AX5+AY5 -> 4140 | BA5: =$E5*AZ5 -> 101513.9 | BB5: 3210 | BC5: 930 | BD5: =BB5+BC5 -> 4140 | BE5: =$E5*BD5 -> 101513.9 | BF5: 3210 | BG5: 930 | BH5: =BF5+BG5 -> 4140 | BI5: =$E5*BH5 -> 101513.9 | BJ5: 3210 | BK5: 930 | BL5: =BJ5+BK5 -> 4140 | BM5: =$E5*BL5 -> 101513.9 | BN5: 3210 | BO5: 930 | BP5: =BN5+BO5 -> 4140 | BQ5: =$E5*BP5 -> 101513.9 | BR5: 3210 | BS5: 930 | BT5: =BR5+BS5 -> 4140 | BU5: =$E5*BT5 -> 101513.9
A6: 10q. Testing / Inspection / QC | B6: Testing / Inspection | D6: C5. Testing / Inspection / QC | E6: 12.958719 | F6: 1530 | G6: 0 | H6: =F6+G6 -> 1530 | I6: =$E6*H6 -> 19826.84 | J6: 1530 | K6: 0 | L6: =J6+K6 -> 1530 | M6: =$E6*L6 -> 19826.84 | N6: 1530 | O6: 0 | P6: =N6+O6 -> 1530 | Q6: =$E6*P6 -> 19826.84 | R6: 1530 | S6: 0 | T6: =R6+S6 -> 1530 | U6: =$E6*T6 -> 19826.84 | V6: 1530 | W6: 0 | X6: =V6+W6 -> 1530 | Y6: =$E6*X6 -> 19826.84 | Z6: 1530 | AA6: 0 | AB6: =Z6+AA6 -> 1530 | AC6: =$E6*AB6 -> 19826.84 | AD6: 1530 | AE6: 0 | AF6: =AD6+AE6 -> 1530 | AG6: =$E6*AF6 -> 19826.84 | AH6: 1530 | AI6: 0 | AJ6: =AH6+AI6 -> 1530 | AK6: =$E6*AJ6 -> 19826.84 | AL6: 1530 | AM6: 0 | AN6: =AL6+AM6 -> 1530 | AO6: =$E6*AN6 -> 19826.84 | AP6: 1530 | AQ6: 0 | AR6: =AP6+AQ6 -> 1530 | AS6: =$E6*AR6 -> 19826.84 | AT6: 1530 | AU6: 0 | AV6: =AT6+AU6 -> 1530 | AW6: =$E6*AV6 -> 19826.84 | AX6: 1530 | AY6: 0 | AZ6: =AX6+AY6 -> 1530 | BA6: =$E6*AZ6 -> 19826.84 | BB6: 1530 | BC6: 0 | BD6: =BB6+BC6 -> 1530 | BE6: =$E6*BD6 -> 19826.84 | BF6: 1530 | BG6: 0 | BH6: =BF6+BG6 -> 1530 | BI6: =$E6*BH6 -> 19826.84 | BJ6: 1530 | BK6: 0 | BL6: =BJ6+BK6 -> 1530 | BM6: =$E6*BL6 -> 19826.84 | BN6: 1530 | BO6: 0 | BP6: =BN6+BO6 -> 1530 | BQ6: =$E6*BP6 -> 19826.84 | BR6: 1530 | BS6: 0 | BT6: =BR6+BS6 -> 1530 | BU6: =$E6*BT6 -> 19826.84
A7: 10b. Rolling / Bending Shell | B7: Rolling / bending | D7: C1. Rolling / Bending Shell | E7: 79.01141 | F7: 390 | G7: 150 | H7: =F7+G7 -> 540 | I7: =$E7*H7 -> 42666.162 | J7: 390 | K7: 150 | L7: =J7+K7 -> 540 | M7: =$E7*L7 -> 42666.162 | N7: 390 | O7: 150 | P7: =N7+O7 -> 540 | Q7: =$E7*P7 -> 42666.162 | R7: 390 | S7: 150 | T7: =R7+S7 -> 540 | U7: =$E7*T7 -> 42666.162 | V7: 390 | W7: 150 | X7: =V7+W7 -> 540 | Y7: =$E7*X7 -> 42666.162 | Z7: 390 | AA7: 150 | AB7: =Z7+AA7 -> 540 | AC7: =$E7*AB7 -> 42666.162 | AD7: 390 | AE7: 150 | AF7: =AD7+AE7 -> 540 | AG7: =$E7*AF7 -> 42666.162 | AH7: 390 | AI7: 150 | AJ7: =AH7+AI7 -> 540 | AK7: =$E7*AJ7 -> 42666.162 | AL7: 390 | AM7: 150 | AN7: =AL7+AM7 -> 540 | AO7: =$E7*AN7 -> 42666.162 | AP7: 390 | AQ7: 150 | AR7: =AP7+AQ7 -> 540 | AS7: =$E7*AR7 -> 42666.162 | AT7: 390 | AU7: 150 | AV7: =AT7+AU7 -> 540 | AW7: =$E7*AV7 -> 42666.162 | AX7: 390 | AY7: 150 | AZ7: =AX7+AY7 -> 540 | BA7: =$E7*AZ7 -> 42666.162 | BB7: 390 | BC7: 150 | BD7: =BB7+BC7 -> 540 | BE7: =$E7*BD7 -> 42666.162 | BF7: 390 | BG7: 150 | BH7: =BF7+BG7 -> 540 | BI7: =$E7*BH7 -> 42666.162 | BJ7: 390 | BK7: 150 | BL7: =BJ7+BK7 -> 540 | BM7: =$E7*BL7 -> 42666.162 | BN7: 390 | BO7: 150 | BP7: =BN7+BO7 -> 540 | BQ7: =$E7*BP7 -> 42666.162 | BR7: 390 | BS7: 150 | BT7: =BR7+BS7 -> 540 | BU7: =$E7*BT7 -> 42666.162
A8: 10d. Machining / Turning Body | B8: Lathe turning | D8: C3. Machining / Turning Body | E8: 42.896028 | F8: 840 | G8: 180 | H8: =F8+G8 -> 1020 | I8: =$E8*H8 -> 43753.948 | J8: 840 | K8: 180 | L8: =J8+K8 -> 1020 | M8: =$E8*L8 -> 43753.948 | N8: 840 | O8: 180 | P8: =N8+O8 -> 1020 | Q8: =$E8*P8 -> 43753.948 | R8: 840 | S8: 180 | T8: =R8+S8 -> 1020 | U8: =$E8*T8 -> 43753.948 | V8: 840 | W8: 180 | X8: =V8+W8 -> 1020 | Y8: =$E8*X8 -> 43753.948 | Z8: 840 | AA8: 180 | AB8: =Z8+AA8 -> 1020 | AC8: =$E8*AB8 -> 43753.948 | AD8: 840 | AE8: 180 | AF8: =AD8+AE8 -> 1020 | AG8: =$E8*AF8 -> 43753.948 | AH8: 840 | AI8: 180 | AJ8: =AH8+AI8 -> 1020 | AK8: =$E8*AJ8 -> 43753.948 | AL8: 840 | AM8: 180 | AN8: =AL8+AM8 -> 1020 | AO8: =$E8*AN8 -> 43753.948 | AP8: 840 | AQ8: 180 | AR8: =AP8+AQ8 -> 1020 | AS8: =$E8*AR8 -> 43753.948 | AT8: 840 | AU8: 180 | AV8: =AT8+AU8 -> 1020 | AW8: =$E8*AV8 -> 43753.948 | AX8: 840 | AY8: 180 | AZ8: =AX8+AY8 -> 1020 | BA8: =$E8*AZ8 -> 43753.948 | BB8: 840 | BC8: 180 | BD8: =BB8+BC8 -> 1020 | BE8: =$E8*BD8 -> 43753.948 | BF8: 840 | BG8: 180 | BH8: =BF8+BG8 -> 1020 | BI8: =$E8*BH8 -> 43753.948 | BJ8: 840 | BK8: 180 | BL8: =BJ8+BK8 -> 1020 | BM8: =$E8*BL8 -> 43753.948 | BN8: 840 | BO8: 180 | BP8: =BN8+BO8 -> 1020 | BQ8: =$E8*BP8 -> 43753.948 | BR8: 840 | BS8: 180 | BT8: =BR8+BS8 -> 1020 | BU8: =$E8*BT8 -> 43753.948
A9: 10p. Assembly + Engineering | B9: Engineering / design | D9: C4. Assembly + Engineering | E9: 17.034091 | F9: 1830 | G9: 0 | H9: =F9+G9 -> 1830 | I9: =$E9*H9 -> 31172.386 | J9: 1830 | K9: 0 | L9: =J9+K9 -> 1830 | M9: =$E9*L9 -> 31172.386 | N9: 1830 | O9: 0 | P9: =N9+O9 -> 1830 | Q9: =$E9*P9 -> 31172.386 | R9: 1830 | S9: 0 | T9: =R9+S9 -> 1830 | U9: =$E9*T9 -> 31172.386 | V9: 1830 | W9: 0 | X9: =V9+W9 -> 1830 | Y9: =$E9*X9 -> 31172.386 | Z9: 1830 | AA9: 0 | AB9: =Z9+AA9 -> 1830 | AC9: =$E9*AB9 -> 31172.386 | AD9: 1830 | AE9: 0 | AF9: =AD9+AE9 -> 1830 | AG9: =$E9*AF9 -> 31172.386 | AH9: 1830 | AI9: 0 | AJ9: =AH9+AI9 -> 1830 | AK9: =$E9*AJ9 -> 31172.386 | AL9: 1830 | AM9: 0 | AN9: =AL9+AM9 -> 1830 | AO9: =$E9*AN9 -> 31172.386 | AP9: 1830 | AQ9: 0 | AR9: =AP9+AQ9 -> 1830 | AS9: =$E9*AR9 -> 31172.386 | AT9: 1830 | AU9: 0 | AV9: =AT9+AU9 -> 1830 | AW9: =$E9*AV9 -> 31172.386 | AX9: 1830 | AY9: 0 | AZ9: =AX9+AY9 -> 1830 | BA9: =$E9*AZ9 -> 31172.386 | BB9: 1830 | BC9: 0 | BD9: =BB9+BC9 -> 1830 | BE9: =$E9*BD9 -> 31172.386 | BF9: 1830 | BG9: 0 | BH9: =BF9+BG9 -> 1830 | BI9: =$E9*BH9 -> 31172.386 | BJ9: 1830 | BK9: 0 | BL9: =BJ9+BK9 -> 1830 | BM9: =$E9*BL9 -> 31172.386 | BN9: 1830 | BO9: 0 | BP9: =BN9+BO9 -> 1830 | BQ9: =$E9*BP9 -> 31172.386 | BR9: 1830 | BS9: 0 | BT9: =BR9+BS9 -> 1830 | BU9: =$E9*BT9 -> 31172.386
A10: 10o. Painting & Surface Prep | B10: Engineering / design | D10: C6. Painting & Surface Prep | E10: 0 | F10: 0 | G10: 0 | H10: =F10+G10 -> 0 | I10: =$E10*H10 -> 0 | J10: 0 | K10: 0 | L10: =J10+K10 -> 0 | M10: =$E10*L10 -> 0 | N10: 0 | O10: 0 | P10: =N10+O10 -> 0 | Q10: =$E10*P10 -> 0 | R10: 0 | S10: 0 | T10: =R10+S10 -> 0 | U10: =$E10*T10 -> 0 | V10: 0 | W10: 0 | X10: =V10+W10 -> 0 | Y10: =$E10*X10 -> 0 | Z10: 0 | AA10: 0 | AB10: =Z10+AA10 -> 0 | AC10: =$E10*AB10 -> 0 | AD10: 0 | AE10: 0 | AF10: =AD10+AE10 -> 0 | AG10: =$E10*AF10 -> 0 | AH10: 0 | AI10: 0 | AJ10: =AH10+AI10 -> 0 | AK10: =$E10*AJ10 -> 0 | AL10: 0 | AM10: 0 | AN10: =AL10+AM10 -> 0 | AO10: =$E10*AN10 -> 0 | AP10: 0 | AQ10: 0 | AR10: =AP10+AQ10 -> 0 | AS10: =$E10*AR10 -> 0 | AT10: 0 | AU10: 0 | AV10: =AT10+AU10 -> 0 | AW10: =$E10*AV10 -> 0 | AX10: 0 | AY10: 0 | AZ10: =AX10+AY10 -> 0 | BA10: =$E10*AZ10 -> 0 | BB10: 0 | BC10: 0 | BD10: =BB10+BC10 -> 0 | BE10: =$E10*BD10 -> 0 | BF10: 0 | BG10: 0 | BH10: =BF10+BG10 -> 0 | BI10: =$E10*BH10 -> 0 | BJ10: 0 | BK10: 0 | BL10: =BJ10+BK10 -> 0 | BM10: =$E10*BL10 -> 0 | BN10: 0 | BO10: 0 | BP10: =BN10+BO10 -> 0 | BQ10: =$E10*BP10 -> 0 | BR10: 0 | BS10: 0 | BT10: =BR10+BS10 -> 0 | BU10: =$E10*BT10 -> 0
F11: =SUM(F5:F10) -> 7800 | G11: =SUM(G5:G10) -> 1260 | H11: =SUM(H5:H10) -> 9060 | I11: =SUM(I5:I10) -> 238933.24 | J11: =SUM(J5:J10) -> 7800 | K11: =SUM(K5:K10) -> 1260 | L11: =SUM(L5:L10) -> 9060 | M11: =SUM(M5:M10) -> 238933.24 | ... BU11: =SUM(BU5:BU10) -> 238933.24

Sheet Delivery Schedule
B1: DRIVE PULLEY — INDIA DELIVERY SCHEDULE | Days from order to dispatch
B3: Sourcing selection (Yellow = override) drives delivery time automatically
B4: Process / Activity | C4: Sourcing | D4: Std. Days | E4: Override Days | F4: Unit | G4: Notes | H4: Model1 | I4: Model2
B5: ── PHASE 0: PLANNING & PROCUREMENT ──
B6: BOM Release & Engineering Sign-off | C6: In-house | D6: 2 | F6: =IF(C6="Outsource",IF(E6<>"",E6,D6),IF(C6="In-house",D6,IF(C6="Logistics",D6,0))) -> 2 | G6: h | H6: Hours converted: ~2h = 0.25 day
B7: Purchasing – Critical Parts | C7: In-house | D7: 5 | F7: =IF(C7="Outsource",IF(E7<>"",E7,D7),IF(C7="In-house",D7,IF(C7="Logistics",D7,0))) -> 5 | G7: days | H7: Internal purchasing dept
B8: ── PHASE 1: PULLEY BODY ──
B9: Shell Plate Procurement | C9: Outsource | D9: 35 | E9: 35 | F9: =IF(C9="Outsource",IF(E9<>"",E9,D9),IF(C9="In-house",D9,IF(C9="Logistics",D9,0))) -> 35 | G9: days | H9: Plate mill lead time
B10: Logistic – Plates to Works | C10: Logistics | D10: 1 | E10: 1 | F10: =IF(C10="Outsource",IF(E10<>"",E10,D10),IF(C10="In-house",D10,IF(C10="Logistics",D10,0))) -> 1 | G10: days
B11: Weld Preparation | C11: In-house | D11: 1 | E11: 2 | F11: =IF(C11="Outsource",IF(E11<>"",E11,D11),IF(C11="In-house",D11,IF(C11="Logistics",D11,0))) -> 1 | G11: days | H11: Calc from geometry
B12: Rolling / Bending + Calibration | C12: In-house | D12: 1 | E12: 2 | F12: =IF(C12="Outsource",IF(E12<>"",E12,D12),IF(C12="In-house",D12,IF(C12="Logistics",D12,0))) -> 1 | G12: days | H12: In-house rolling
B13: Tacking & Grinding Shell | C13: In-house | D13: 1 | E13: 1 | F13: =IF(C13="Outsource",IF(E13<>"",E13,D13),IF(C13="In-house",D13,IF(C13="Logistics",D13,0))) -> 1 | G13: days
B14: Heat-up & Longitudinal Weld | C14: In-house | D14: 1 | E14: 1 | F14: =IF(C14="Outsource",IF(E14<>"",E14,D14),IF(C14="In-house",D14,IF(C14="Logistics",D14,0))) -> 1 | G14: days
B15: Ready Tube (outsourced shell option) | C15: Outsource | D15: 40 | E15: 14 | F15: =IF(C15="Outsource",IF(E15<>"",E15,D15),IF(C15="In-house",D15,IF(C15="Logistics",D15,0))) -> 14 | G15: days | H15: If tube outsourced: 14d
B16: Logistic – Ready Tube | C16: Logistics | D16: 0 | E16: 1 | F16: =IF(C16="Outsource",IF(E16<>"",E16,D16),IF(C16="In-house",D16,IF(C16="Logistics",D16,0))) -> 0 | G16: days | H16: Only if outsourced
B17: Hub Material Procurement | C17: Outsource | D17: 35 | E17: 35 | F17: =IF(C17="Outsource",IF(E17<>"",E17,D17),IF(C17="In-house",D17,IF(C17="Logistics",D17,0))) -> 35 | G17: days | H17: Cast / forged hub
B18: Logistic – Hub Material | C18: Logistics | D18: 1 | E18: 1 | F18: =IF(C18="Outsource",IF(E18<>"",E18,D18),IF(C18="In-house",D18,IF(C18="Logistics",D18,0))) -> 1 | G18: days
B19: Hub Pre-Turning | C19: In-house | D19: 2 | E19: 5 | F19: =IF(C19="Outsource",IF(E19<>"",E19,D19),IF(C19="In-house",D19,IF(C19="Logistics",D19,0))) -> 2 | G19: days | H19: Depends on size
B20: Hub-to-Shell Tacking & Grinding | C20: In-house | D20: 1 | E20: 2 | F20: =IF(C20="Outsource",IF(E20<>"",E20,D20),IF(C20="In-house",D20,IF(C20="Logistics",D20,0))) -> 1 | G20: days
B21: Hub-to-Shell Weld | C21: In-house | D21: 1 | E21: 2 | F21: =IF(C21="Outsource",IF(E21<>"",E21,D21),IF(C21="In-house",D21,IF(C21="Logistics",D21,0))) -> 1 | G21: days
B22: ── PHASE 2: POST-WELD PROCESSING ──
B23: Stress Relief Annealing | C23: Outsource | D23: 7 | E23: 7 | F23: =IF(C23="Outsource",IF(E23<>"",E23,D23),IF(C23="In-house",D23,IF(C23="Logistics",D23,0))) -> 7 | G23: days | H23: Outsourced heat treater
B24: Logistic – Stress Relief (both ways) | C24: Logistics | D24: 6 | E24: 6 | F24: =IF(C24="Outsource",IF(E24<>"",E24,D24),IF(C24="In-house",D24,IF(C24="Logistics",D24,0))) -> 6 | G24: days | H24: To/from heat treater
B25: Machining – Body (turning, boring, facing) | C25: Outsource | D25: 7 | E25: 10 | F25: =IF(C25="Outsource",IF(E25<>"",E25,D25),IF(C25="In-house",D25,IF(C25="Logistics",D25,0))) -> 10 | G25: days | H25: Can be in-house or outsourced
B26: Test & Dynamic Balancing | C26: In-house | D26: 3 | E26: 3 | F26: =IF(C26="Outsource",IF(E26<>"",E26,D26),IF(C26="In-house",D26,IF(C26="Logistics",D26,0))) -> 3 | G26: days
B27: ── PHASE 3: PURCHASED COMPONENTS ──
B28: Shaft (Procurement / Machining) | C28: Outsource | D28: 84 | E28: 84 | F28: =IF(C28="Outsource",IF(E28<>"",E28,D28),IF(C28="In-house",D28,IF(C28="Logistics",D28,0))) -> 84 | G28: days | H28: Forged shaft lead time
B29: Bearing (Procurement) | C29: Outsource | D29: 60 | E29: 60 | F29: =IF(C29="Outsource",IF(E29<>"",E29,D29),IF(C29="In-house",D29,IF(C29="Logistics",D29,0))) -> 60 | G29: days | H29: SKF/FAG India: 60-120d
B30: Bearing Housing (Procurement) | C30: Outsource | D30: 84 | E30: 84 | F30: =IF(C30="Outsource",IF(E30<>"",E30,D30),IF(C30="In-house",D30,IF(C30="Logistics",D30,0))) -> 84 | G30: days | H30: MASTA/SKF housing
B31: Adapter Sleeve (Procurement) | C31: Outsource | D31: 30 | E31: 60 | F31: =IF(C31="Outsource",IF(E31<>"",E31,D31),IF(C31="In-house",D31,IF(C31="Logistics",D31,0))) -> 60 | G31: days
B32: Locking Device (Procurement) | C32: Outsource | D32: 60 | E32: 60 | F32: =IF(C32="Outsource",IF(E32<>"",E32,D32),IF(C32="In-house",D32,IF(C32="Logistics",D32,0))) -> 60 | G32: days | H32: NMTG / BIKON
B33: ── PHASE 4: LAGGING ──
B34: Lagging Application | C34: Outsource | D34: 14 | E34: 14 | F34: =IF(C34="Outsource",IF(E34<>"",E34,D34),IF(C34="In-house",D34,IF(C34="Logistics",D34,0))) -> 14 | G34: days | H34: Rubber hot vulcanised
B35: Logistic – Lagging (both ways) | C35: Logistics | D35: 2 | E35: 2 | F35: =IF(C35="Outsource",IF(E35<>"",E35,D35),IF(C35="In-house",D35,IF(C35="Logistics",D35,0))) -> 2 | G35: days
B36: ── PHASE 5: FINAL ASSEMBLY & DISPATCH ──
B37: Final Assembly & Inspection | C37: In-house | D37: 3 | E37: 4 | F37: =IF(C37="Outsource",IF(E37<>"",E37,D37),IF(C37="In-house",D37,IF(C37="Logistics",D37,0))) -> 3 | G37: days
B38: Painting & Packing | C38: In-house | D38: 3 | E38: 4 | F38: =IF(C38="Outsource",IF(E38<>"",E38,D38),IF(C38="In-house",D38,IF(C38="Logistics",D38,0))) -> 3 | G38: days
B39: Weekend Buffer | C39: — | D39: 5 | E39: 5 | F39: =IF(C39="Outsource",IF(E39<>"",E39,D39),IF(C39="In-house",D39,IF(C39="Logistics",D39,0))) -> 0 | G39: days | H39: ~10% for weekends
B41: TOTAL CALENDAR DAYS (Parallel-path critical items) | F41: =MAX(F28:F32)+F6+F7+F23+F24+F25+F26+F34+F35+F37+F38+F39 -> 139 | G41: calendar
B42: → Delivery Weeks (÷7, apply safety factor) | F42: =F41/7*'Cost Rate Tables'!C9 -> 23.828571
B44: NOTE: Actual lead time is driven by the CRITICAL PATH (longest parallel chain). Typically: Bearing/Housing (98-120 days) or Shaft (84 days) determines the schedule. Body manufacturing (81 days) usually runs in parallel. Change sourcing to 'Outsource' to activate outsourced lead times.

Sheet MHR & LHR Calculator
B1: MACHINE HOUR RATE (MHR) & LABOUR HOUR RATE (LHR) CALCULATOR
B2: India Operations | All rates auto-feed into Cost Rate Tables
B4: COST ELEMENT | C4: Unit | D4: Lathe / Turning | E4: Rolling / Bending | F4: Welding (MIG/MAG) | G4: Grinding / Finishing | H4: Assembly | I4: Painting / Blasting | J4: Engineering
B5: 1. MACHINE CAPACITY & AVAILABILITY
B6: Working Days per Year | C6: days | D6: 300 | E6: 300 | F6: 300 | G6: 300 | H6: 300 | I6: 300 | J6: 250
B7: Shifts per Day | C7: shifts | D7: 2 | E7: 2 | F7: 2 | G7: 2 | H7: 1 | I7: 1 | J7: 1
B8: Hours per Shift | C8: h/shift | D8: 8 | E8: 8 | F8: 8 | G8: 8 | H8: 8 | I8: 8 | J8: 8
B9: Total Available Hours / Year [auto] | C9: h/yr | D9: =D6*D7*D8 -> 4800 | E9: =E6*E7*E8 -> 4800 | F9: =F6*F7*F8 -> 4800 | G9: =G6*G7*G8 -> 4800 | H9: =H6*H7*H8 -> 2400 | I9: =I6*I7*I8 -> 2400 | J9: =J6*J7*J8 -> 2000
B10: Planned Machine Utilisation % | C10: % | D10: 0.75 | E10: 0.7 | F10: 0.8 | G10: 0.7 | H10: 0.75 | I10: 0.65 | J10: 0.85
B11: Effective Productive Hours / Year [auto] | C11: h/yr | D11: =D9*D10 -> 3600 | E11: =E9*E10 -> 3360 | F11: =F9*F10 -> 3840 | G11: =G9*G10 -> 3360 | H11: =H9*H10 -> 1800 | I11: =I9*I10 -> 1560 | J11: =J9*J10 -> 1700
B13: 2. MACHINE ANNUAL COSTS (INR per year)
B14: Machine Purchase / Replacement Cost | C14: INR | D14: 4500000 | E14: 6500000 | F14: 1200000 | G14: 1800000 | H14: 500000 | I14: 900000 | J14: 0
B15: Machine Life (years) | C15: years | D15: 10 | E15: 15 | F15: 10 | G15: 10 | H15: 7 | I15: 7 | J15: 0
B16: Residual / Scrap Value % | C16: % | D16: 0.1 | E16: 0.1 | F16: 0.1 | G16: 0.1 | H16: 0.1 | I16: 0.1 | J16: 0.1
B17: Depreciation / year [auto: SLM] | C17: INR/yr | D17: =IF(D15>0,D14*(1-D16)/D15,0) -> 405000 | E17: =IF(E15>0,E14*(1-E16)/E15,0) -> 390000 | F17: =IF(F15>0,F14*(1-F16)/F15,0) -> 108000 | G17: =IF(G15>0,G14*(1-G16)/G15,0) -> 162000 | H17: =IF(H15>0,H14*(1-H16)/H15,0) -> 64285.714 | I17: =IF(I15>0,I14*(1-I16)/I15,0) -> 115714.29 | J17: =IF(J15>0,J14*(1-J16)/J15,0) -> 0
B18: Connected Load (kW) | C18: kW | D18: 18.5 | E18: 22 | F18: 5 | G18: 7.5 | H18: 0 | I18: 2.2 | J18: 0
B19: Average Load Factor | C19: % | D19: 0.7 | E19: 0.65 | F19: 0.85 | G19: 0.72 | H19: 0.5 | I19: 0.55 | J19: 0
B20: Electricity Tariff (INR/kWh) | C20: INR/kWh | D20: 8.5 | E20: 8.5 | F20: 8.5 | G20: 8.5 | H20: 8.5 | I20: 8.5 | J20: 8.5
B21: Power Cost / year [auto] | C21: INR/yr | D21: =D18*D19*D20*D9 -> 528360 | E21: =E18*E19*E20*E9 -> 583440 | F21: =F18*F19*F20*F9 -> 173400 | G21: =G18*G19*G20*G9 -> 220320 | H21: =H18*H19*H20*H9 -> 0 | I21: =I18*I19*I20*I9 -> 24684 | J21: =J18*J19*J20*J9 -> 0
B22: Maintenance Cost % of Machine Value | C22: % | D22: 0.05 | E22: 0.04 | F22: 0.06 | G22: 0.05 | H22: 0.03 | I22: 0.04 | J22: 0.02
B23: Maintenance Cost / year [auto] | C23: INR/yr | D23: =D14*D22 -> 225000 | E23: =E14*E22 -> 260000 | F23: =F14*F22 -> 72000 | G23: =G14*G22 -> 90000 | H23: =H14*H22 -> 15000 | I23: =I14*I22 -> 36000 | J23: =J14*J22 -> 0
B24: Consumables & Tooling (INR/year) | C24: INR/yr | D24: 240000 | E24: 96000 | F24: 180000 | G24: 120000 | H24: 48000 | I24: 96000 | J24: 0
B25: Floor Space Area (m²) | C25: m² | D25: 40 | E25: 80 | F25: 20 | G25: 25 | H25: 60 | I25: 50 | J25: 20
B26: Factory Rent / m² / month (INR) | C26: INR/m² | D26: 45 | E26: 45 | F26: 45 | G26: 45 | H26: 45 | I26: 45 | J26: 45
B27: Floor Rent / year [auto] | C27: INR/yr | D27: =D25*D26*12 -> 21600 | E27: =E25*E26*12 -> 43200 | F27: =F25*F26*12 -> 10800 | G27: =G25*G26*12 -> 13500 | H27: =H25*H26*12 -> 32400 | I27: =I25*I26*12 -> 27000 | J27: =J25*J26*12 -> 10800
B28: Insurance (INR/year) | C28: INR/yr | D28: 18000 | E28: 24000 | F28: 8000 | G28: 10000 | H28: 5000 | I28: 6000 | J28: 0
B29: Factory Overhead Allocation (INR/year) | C29: INR/yr | D29: 360000 | E29: 480000 | F29: 180000 | G29: 240000 | H29: 120000 | I29: 180000 | J29: 120000
B31: TOTAL MACHINE COST / YEAR (INR)
B32: Total Machine Cost / Year [auto] | C32: INR/yr | D32: =D17+D21+D23+D24+D27+D28+D29 -> 1797960 | E32: =E17+E21+E23+E24+E27+E28+E29 -> 1876640 | F32: =F17+F21+F23+F24+F27+F28+F29 -> 732200 | G32: =G17+G21+G23+G24+G27+G28+G29 -> 855820 | H32: =H17+H21+H23+H24+H27+H28+H29 -> 284685.71 | I32: =I17+I21+I23+I24+I27+I28+I29 -> 485398.29 | J32: =J17+J21+J23+J24+J27+J28+J29 -> 130800
B34: 3. LABOUR COST INPUTS (per machine / workstation)
B35: No. of Operators per Machine | C35: nos | D35: 1 | E35: 1 | F35: 1 | G35: 1 | H35: 2 | I35: 1 | J35: 0
B36: Operator Salary / month (CTC, INR) | C36: INR/mo | D36: 28000 | E36: 32000 | F36: 35000 | G36: 30000 | H36: 25000 | I36: 25000 | J36: 0
B37: Operator Annual Cost [auto: ×13.5 incl. bonus] | C37: INR/yr | D37: =D35*D36*13.5 -> 378000 | E37: =E35*E36*13.5 -> 432000 | F37: =F35*F36*13.5 -> 472500 | G37: =G35*G36*13.5 -> 405000 | H37: =H35*H36*13.5 -> 675000 | I37: =I35*I36*13.5 -> 337500 | J37: =J35*J36*13.5 -> 0
B38: Supervisor Salary / month (CTC, INR) | C38: INR/mo | D38: 55000 | E38: 55000 | F38: 55000 | G38: 55000 | H38: 45000 | I38: 45000 | J38: 80000
B39: No. of Machines Supervised (shared) | C39: nos | D39: 3 | E39: 3 | F39: 3 | G39: 3 | H39: 3 | I39: 3 | J39: 3
B40: Supervisor Cost Allocated / Machine [auto] | C40: INR/yr | D40: =IF(D39>0,D38*13.5/D39,0) -> 247500 | E40: =IF(E39>0,E38*13.5/E39,0) -> 247500 | F40: =IF(F39>0,F38*13.5/F39,0) -> 247500 | G40: =IF(G39>0,G38*13.5/G39,0) -> 247500 | H40: =IF(H39>0,H38*13.5/H39,0) -> 202500 | I40: =IF(I39>0,I38*13.5/I39,0) -> 202500 | J40: =IF(J39>0,J38*13.5/J39,0) -> 360000
B41: No. of Helper / Unskilled Workers | C41: nos | D41: 0 | E41: 1 | F41: 1 | G41: 0 | H41: 1 | I41: 1 | J41: 0
B42: Helper Salary / month (INR) | C42: INR/mo | D42: 18000 | E42: 18000 | F42: 18000 | G42: 18000 | H42: 18000 | I42: 18000 | J42: 18000
B43: Helper Annual Cost [auto] | C43: INR/yr | D43: =D41*D42*13.5 -> 0 | E43: =E41*E42*13.5 -> 243000 | F43: =F41*F42*13.5 -> 243000 | G43: =G41*G42*13.5 -> 0 | H43: =H41*H42*13.5 -> 243000 | I43: =I41*I42*13.5 -> 243000 | J43: =J41*J42*13.5 -> 0
B44: ESI / PF / Gratuity (% of salary bill) | C44: % | D44: 0.2 | E44: 0.2 | F44: 0.2 | G44: 0.2 | H44: 0.2 | I44: 0.2 | J44: 0.2
B45: Statutory Contributions [auto] | C45: INR/yr | D45: =(D37+D40+D43)*D44 -> 125100 | E45: =(E37+E40+E43)*E44 -> 184500 | F45: =(F37+F40+F43)*F44 -> 192600 | G45: =(G37+G40+G43)*G44 -> 130500 | H45: =(H37+H40+H43)*H44 -> 224100 | I45: =(I37+I40+I43)*I44 -> 156600 | J45: =(J37+J40+J43)*J44 -> 72000
B46: Safety / PPE / Training (INR/year) | C46: INR/yr | D46: 12000 | E46: 18000 | F46: 24000 | G46: 12000 | H46: 12000 | I46: 18000 | J46: 12000
B48: TOTAL LABOUR COST / YEAR (INR)
B49: Total Labour Cost / Year [auto] | C49: INR/yr | D49: =D37+D40+D43+D45+D46 -> 762600 | E49: =E37+E40+E43+E45+E46 -> 1125000 | F49: =F37+F40+F43+F45+F46 -> 1179600 | G49: =G37+G40+G43+G45+G46 -> 795000 | H49: =H37+H40+H43+H45+H46 -> 1356600 | I49: =I37+I40+I43+I45+I46 -> 957600 | J49: =J37+J40+J43+J45+J46 -> 444000
B51: 4. RATE CALCULATION — MHR & LHR (INR / Productive Hour)
B52: Total Cost (Machine + Labour) / Year [auto] | C52: INR/yr | D52: =D32+D49 -> 2560560 | E52: =E32+E49 -> 3001640 | F52: =F32+F49 -> 1911800 | G52: =G32+G49 -> 1650820 | H52: =H32+H49 -> 1641285.7 | I52: =I32+I49 -> 1442998.3 | J52: =J32+J49 -> 574800
B53: ◆ MACHINE HOUR RATE (MHR) [auto] | C53: INR/h | D53: =IFERROR(D32/D11,0) -> 499.43333 | E53: =IFERROR(E32/E11,0) -> 558.52381 | F53: =IFERROR(F32/F11,0) -> 190.67708 | G53: =IFERROR(G32/G11,0) -> 254.70833 | H53: =IFERROR(H32/H11,0) -> 158.15873 | I53: =IFERROR(I32/I11,0) -> 311.15275 | J53: =IFERROR(J32/J11,0) -> 76.941176
B54: ◆ LABOUR HOUR RATE (LHR) [auto] | C54: INR/h | D54: =IFERROR(D49/D11,0) -> 211.83333 | E54: =IFERROR(E49/E11,0) -> 334.82143 | F54: =IFERROR(F49/F11,0) -> 307.1875 | G54: =IFERROR(G49/G11,0) -> 236.60714 | H54: =IFERROR(H49/H11,0) -> 753.66667 | I54: =IFERROR(I49/I11,0) -> 613.84615 | J54: =IFERROR(J49/J11,0) -> 261.17647
B55: ◆ COMBINED RATE (MHR + LHR) ← feeds Cost Rate Tables | C55: INR/h | D55: =D53+D54 -> 711.26667 | E55: =E53+E54 -> 893.34524 | F55: =F53+F54 -> 497.86458 | G55: =G53+G54 -> 491.31548 | H55: =H53+H54 -> 911.8254 | I55: =I53+I54 -> 924.9989 | J55: =J53+J54 -> 338.11765
B56: MHR only (machine cost only) | C56: INR/h | D56: =D53 -> 499.43333 | E56: =E53 -> 558.52381 | F56: =F53 -> 190.67708 | G56: =G53 -> 254.70833 | H56: =H53 -> 158.15873 | I56: =I53 -> 311.15275 | J56: =J53 -> 76.941176
B57: LHR only (labour cost only) | C57: INR/h | D57: =D54 -> 211.83333 | E57: =E54 -> 334.82143 | F57: =F54 -> 307.1875 | G57: =G54 -> 236.60714 | H57: =H54 -> 753.66667 | I57: =I54 -> 613.84615 | J57: =J54 -> 261.17647
B59: 5. STANDARD OPERATION TIMES (hours per tonne of pulley body)
B60: Standard times below are hours per tonne of pulley body mass. Override yellow cells. Total INR/tonne and INR/kg auto-calculated from combined rate above.
B61: Operation | C61: Unit | D61: Lathe | E61: Rolling | F61: Welding | G61: Grinding | H61: Assembly | I61: Painting | J61: Engineering
B62: Shell body turning | C62: h/tonne | D62: 3.5 | E62: 0 | F62: 0 | G62: 0 | H62: 0 | I62: 0 | J62: 0
B63: Rolling / bending shell | C63: h/tonne | D63: 0 | E63: 2 | F63: 0 | G63: 0 | H63: 0 | I63: 0 | J63: 0
B64: Longitudinal weld | C64: h/tonne | D64: 0 | E64: 0 | F64: 2.5 | G64: 0 | H64: 0 | I64: 0 | J64: 0
B65: Hub turning | C65: h/tonne | D65: 2 | E65: 0 | F65: 0 | G65: 0 | H65: 0 | I65: 0 | J65: 0
B66: Hub-shell weld | C66: h/tonne | D66: 0 | E66: 0 | F66: 3 | G66: 0 | H66: 0 | I66: 0 | J66: 0
B67: Grinding / finishing | C67: h/tonne | D67: 0 | E67: 0 | F67: 0 | G67: 1.5 | H67: 0 | I67: 0 | J67: 0
B68: Assembly | C68: h/tonne | D68: 0 | E68: 0 | F68: 0 | G68: 0 | H68: 2.5 | I68: 0 | J68: 0
B69: Surface prep / painting | C69: h/tonne | D69: 0 | E69: 0 | F69: 0 | G69: 0 | H69: 0 | I69: 1.2 | J69: 0
B70: Engineering & design | C70: h/order | D70: 0 | E70: 0 | F70: 0 | G70: 0 | H70: 0 | I70: 0 | J70: 20
B72: COST PER TONNE (INR/tonne at combined MHR+LHR rate)
B73: Total In-house Processing Cost / tonne [auto] | C73: INR/t | D73: =D62*D55+D63*D55+D64*D55+D65*D55+D66*D55+D67*D55+D68*D55+D69*D55+D70*D55 -> 3911.9667 | E73: =E62*E55+E63*E55+E64*E55+E65*E55+E66*E55+E67*E55+E68*E55+E69*E55+E70*E55 -> 1786.6905 | F73: =F62*F55+F63*F55+F64*F55+F65*F55+F66*F55+F67*F55+F68*F55+F69*F55+F70*F55 -> 2738.2552 | G73: =G62*G55+G63*G55+G64*G55+G65*G55+G66*G55+G67*G55+G68*G55+G69*G55+G70*G55 -> 736.97321 | H73: =H62*H55+H63*H55+H64*H55+H65*H55+H66*H55+H67*H55+H68*H55+H69*H55+H70*H55 -> 2279.5635 | I73: =I62*I55+I63*I55+I64*I55+I65*I55+I66*I55+I67*I55+I68*I55+I69*I55+I70*I55 -> 1109.9987 | J73: =J62*J55+J63*J55+J64*J55+J65*J55+J66*J55+J67*J55+J68*J55+J69*J55+J70*J55 -> 6762.3529
B74: → Cost per kg (INR/kg) [auto] | C74: INR/kg | D74: =D73/1000 -> 3.9119667 | E74: =E73/1000 -> 1.7866905 | F74: =F73/1000 -> 2.7382552 | G74: =G73/1000 -> 0.73697321 | H74: =H73/1000 -> 2.2795635 | I74: =I73/1000 -> 1.1099987 | J74: =J73/1000 -> 6.7623529
B76: 6. COST RATE TABLE FEED — VALUES PUSHED TO 'Cost Rate Tables' SHEET
B77: The 'Cost Rate Tables' sheet references the combined rates below directly. Change inputs above → rates update → all pricing auto-recalculates.
B78: Lathe / Turning rate → Cost Rate Tables C22 | C78: INR/h | D78: =D55 -> 711.26667 | E78: ← Auto-feeds from D55 (Lathe / Turning)
B79: Rolling / Bending rate → C23 | C79: INR/h | D79: =E55 -> 893.34524 | E79: ← Auto-feeds from E55 (Rolling / Bending)
B80: Welding rate → C24 | C80: INR/h | D80: =F55 -> 497.86458 | E80: ← Auto-feeds from F55 (Welding (MIG/MAG))
B81: Grinding / Finishing rate → C25 | C81: INR/h | D81: =G55 -> 491.31548 | E81: ← Auto-feeds from G55 (Grinding / Finishing)
B82: Assembly Labour rate → C26 | C82: INR/h | D82: =H55 -> 911.8254 | E82: ← Auto-feeds from H55 (Assembly)
B83: Painting / Blasting rate → C31 | C83: INR/h | D83: =I55 -> 924.9989 | E83: ← Auto-feeds from I55 (Painting / Blasting)
B84: Engineering rate → C27 | C84: INR/h | D84: =J55 -> 338.11765 | E84: ← Auto-feeds from J55 (Engineering)

Sheet BRG_DATA
A1: Designation | B1: Bore d (mm) | C1: INR/piece | D1: EUR/piece | E1: Delivery (days)
A2: 21316 EK | B2: 80 | C2: 9270 | D2: 84.27 | E2: 60
A3: 22209 EK | B3: 45 | C3: 2958 | D3: 26.89 | E3: 60
A4: 22210 EK | B4: 50 | C4: 2232 | D4: 20.29 | E4: 60
A5: 22211 EK | B5: 55 | C5: 3473 | D5: 31.57 | E5: 60
A6: 22213 E | B6: 65 | C6: 3831 | D6: 34.83 | E6: 60
A7: 22215 EK | B7: 75 | C7: 5801 | D7: 52.74 | E7: 60
A8: 22216 EK | B8: 80 | C8: 4330 | D8: 39.36 | E8: 60
A9: 22217 EK | B9: 85 | C9: 4620 | D9: 42 | E9: 60
A10: 22218 EK | B10: 90 | C10: 10234 | D10: 93.13 | E10: 60
A11: 22219 EK | B11: 95 | C11: 7383 | D11: 67.19 | E11: 60
A12: 22220 EK | B12: 100 | C12: 6900 | D12: 62.79 | E12: 60
A13: 22222 EK | B13: 110 | C13: 7356 | D13: 66.94 | E13: 60
... A48: 23144 CCK/W33 | B48: 220 | C48: 74531 | D48: 678.23 | E48: 60
A49: 23148 CCK/W33 | B49: 240 | C49: 58110 | D49: 797.24 | E49: 60 | F49: Rate Based on Actuals
A50: 23152 CCK/W33 | B50: 260 | C50: 150761 | D50: 1371.93 | E50: 60
A51: 23156 CCK/W33 | B51: 280 | C51: 134692 | D51: 1224.47 | E51: 60
A52: 23160 CCK/W33 | B52: 300 | C52: 197823 | D52: 1800.19 | E52: 60
A53: 23164 CCK/W33 | B53: 320 | C53: 185965 | D53: 1692.28 | E53: 90
A54: 23168 CCK/W33 | B54: 340 | C54: 215156 | D54: 1957.92 | E54: 90
A55: 23172 CCK/W33 | B55: 360 | C55: 298196 | D55: 2710.87 | E55: 90
A56: 23176 CAK/W33 | B56: 380 | C56: 456689 | D56: 4151.72 | E56: 90
A57: 23180 CAK/W33 | B57: 400 | C57: 469516 | D57: 4268.33 | E57: 120
A58: 23184 CKJ/W33 | B58: 420 | C58: 583358 | D58: 5303.25 | E58: 120
A59: 23188 CAK/W33 | B59: 440 | C59: 725745 | D59: 6597.68 | E59: 120
A60: 23192 CAK/W33 | B60: 460 | C60: 720030 | D60: 6545.72 | E60: 120
A61: 23196 CAK/W33 | B61: 480 | C61: 924152 | D61: 8401.38 | E61: 120
... A95: 241/850 ECAK30F/W33 | B95: 850 | C95: 5826700 | D95: 52970 | E95: 120
A96: 22232 CCK/W33 | B96: 160 | C96: 30000 | D96: =C96/108 -> 277.77778 | E96: 60
A97: 22234 CCK/W33 | B97: 170 | C97: 34000 | D97: =C97/108 -> 314.81481

Sheet SL_DATA
A1: For Bearing (key) | B1: Sleeve Code | C1: EUR/piece | D1: INR/piece | E1: Delivery (days)
A2: 21316 EK | B2: H 316 | C2: 16.83 | D2: 1851 | E2: 30
A3: 22209 EK | B3: H 309 | C3: 4.06 | D3: 447 | E3: 30
A4: 22210 EK | B4: H 310 | C4: 4.6 | D4: 506 | E4: 30
A5: 22211 EK | B5: H 311 | C5: 4.68 | D5: 515 | E5: 30
A6: 22213 E | B6: H 313 | C6: 7.97 | D6: 877 | E6: 30
A7: 22215 EK | B7: H 315 | C7: 9.6 | D7: 1056 | E7: 30
A8: 22216 EK | B8: H 316 | C8: 17.67 | D8: 1944 | E8: 30
A9: 22217 EK | B9: H 317 | C9: 13.62 | D9: 1498 | E9: 30
A10: 22218 EK | B10: H 318 | C10: 13 | D10: 1430 | E10: 30
A11: 22219 EK | B11: H 319 | C11: 17.79 | D11: 1957 | E11: 30
A12: 22220 EK | B12: H 320 | C12: 20.23 | D12: 2225 | E12: 30
A13: 22222 EK | B13: H 322 | C13: 13.31 | D13: 1464 | E13: 30
... A41: 23144 CCK/W33 | B41: H 3144 | C41: 122.77 | D41: 13505 | E41: 30
A42: 23148 CCK/W33 | B42: OH 3148 H | C42: 406.04 | D42: 18460 | E42: 75 | F42: Based on Actuls
A43: 23152 CCK/W33 | B43: OH 3152 H | C43: 403.13 | D43: 44344 | E43: 75
A44: 23156 CCK/W33 | B44: OH 3156 H | C44: 470.95 | D44: 51805 | E44: 75
A45: 23160 CCK/W33 | B45: OH 3160 H | C45: 534.17 | D45: 58759 | E45: 75
A46: 23164 CCK/W33 | B46: OH 3164 H | C46: 647.75 | D46: 71253 | E46: 75
A47: 23168 CCK/W33 | B47: OH 3168 H | C47: 1628.1 | D47: 179091 | E47: 75
A48: 23172 CCK/W33 | B48: OH 3172 H | C48: 1163.44 | D48: 127978 | E48: 75
A49: 23176 CAK/W33 | B49: OH 3176 H | C49: 2264.16 | D49: 249058 | E49: 75
A50: 23180 CAK/W33 | B50: OH 3180 H | C50: 2429.9 | D50: 267289 | E50: 90
A51: 23184 CKJ/W33 | B51: OH 3184 H | C51: 2567.24 | D51: 282396 | E51: 90
A52: 23188 CAK/W33 | B52: H 3188 H | C52: 2329.11 | D52: 256202 | E52: 90
A53: 23192 CAK/W33 | B53: H 3192 H | C53: 2674.76 | D53: 294224 | E53: 90
A54: 23196 CAK/W33 | B54: OH 3196 H | C54: 3556.68 | D54: 391235 | E54: 90
... A74: 24148 CCK/W33 | B74: OH 3048 H | C74: 498.29 | D74: 54812 | E74: 75
A75: 24156 CCK/W33 | B75: OH 3056 H | D75: 61600 | E75: 75
A76: 24160 CCK/W33 | B76: OH 3060 H | C76: 678.35 | D76: 74619 | E76: 75
A77: 24172 ECCK30J/W33 | B77: OH 3172 H | C77: 1163.44 | D77: 127978 | E77: 75
A78: 24180 ECAK30/W33 | B78: OH 3180 H | C78: 2429.9 | D78: 267289 | E78: 90
A79: 241/500 ECAK30/W33 | B79: H 241/500 HG | D79: 412259 | E79: 90
A80: 241/530 ECAK30/W33 | B80: H 241/530 HG | E80: 90
A81: 22232 CCK/W33 | B81: H 3132 | C81: 5000 | D81: 5000 | E81: 90
A82: 22234 CCK/W33 | B82: H 3134 | C82: 5000 | D82: 5000 | E82: 90

Sheet HSG_DATA
A1: For Bearing (key) | B1: Housing Designation | C1: INR/piece | D1: Delivery (days)
A2: 22211 EK | B2: SNL 511-609 | C2: 2917 | D2: 98
A3: 22213 E | B3: SNL 513-611 | C3: 3999 | D3: 98
A4: 22215 EK | B4: SNL 515-612 | C4: 4425 | D4: 98
A5: 22216 EK | B5: SNL 516-613 | C5: 5470 | D5: 98
A6: 22217 EK | B6: SNL 517 | C6: 5879 | D6: 98
A7: 22218 EK | B7: SNL 518-615 | C7: 9022 | D7: 98
A8: 22219 EK | B8: SNL 519-616 | C8: 9927 | D8: 98
A9: 22220 EK | B9: SNL 520-617 | C9: 10845 | D9: 98
A10: 22222 EK | B10: SNL 522-619 | C10: 13057 | D10: 98
A11: 22224 EK | B11: FSNL 524-620 | C11: 16738 | D11: 98
A12: 22226 EK | B12: SNL 526 | C12: 20742 | D12: 98
A13: 22228 CCK/W33 | B13: SNL 528 | C13: 25766 | D13: 98
... A74: 232/600 CAK/W33 | B74: SNL 32/600 | C74: 680000 | D74: 120

Sheet LAG_DATA
A1: Lagging Type (key) | B1: Thickness (mm) | C1: INR/m² | D1: Delivery (days) | E1: Description
A2: Rubber vulc. 12mm | B2: 12 | C2: 19387 | D2: 14 | E2: Rubber hot vulcanized 12mm
A3: Rubber vulc. 15mm | B3: 15 | C3: 20702 | D3: 14 | E3: Rubber hot vulcanized 15mm
A4: Rubber vulc. 20mm | B4: 20 | C4: 22439 | D4: 14 | E4: Rubber hot vulcanized 20mm
A5: Rubber vulc. 25mm | B5: 25 | C5: 24222 | D5: 14 | E5: Rubber hot vulcanized 25mm
A6: Rubber vulc. 30mm | B6: 30 | C6: 26241 | D6: 14 | E6: Rubber hot vulcanized 30mm
A7: Rubber ceramic 15mm | B7: 15 | C7: 27344 | D7: 14 | E7: Rubber + ceramic inserts 15mm
A8: Rubber ceramic 20mm | B8: 20 | C8: 29574 | D8: 14 | E8: Rubber + ceramic inserts 20mm
A9: Rubber ceramic 25mm | B9: 25 | C9: 31828 | D9: 14 | E9: Rubber + ceramic inserts 25mm
A10: Ceramic tile 6mm | B10: 6 | C10: 148661 | D10: 7 | E10: Full ceramic tiles 6mm
A11: Ceramic tile 10mm | B11: 10 | C11: 193950 | D11: 7 | E11: Full ceramic tiles 10mm
A12: No lagging | B12: 0 | C12: 0 | D12: 0 | E12: No lagging — bare shell

Sheet LCD_DATA
A2: Model / Size | B2: Indicative price per No. (₹) | C2: Negotiated Rate | D2: Remarks
A3: NMTG N7036-100 × 150 | B3: ₹25,000 – ₹35,000 | C3: 30000 | D3: Estimate
A4: NMTG N7036-120 × 170 | B4: ₹32,000 – ₹45,000 | C4: 40000 | D4: Estimate
A5: NMTG N7036-140 × 200 | B5: ₹42,000 – ₹58,000 | C5: 50000 | D5: Estimate
A6: NMTG N7036-170 × 240 | B6: ₹60,000 – ₹80,000 | C6: 70000 | D6: Estimate
A7: NMTG N7036-180 × 250 | B7: ₹65,000 – ₹90,000 | C7: 80000 | D7: Estimate
